[
  {
    "cid": "6255",
    "title": "[明日方舟]05月22日16:00闪断更新公告",
    "tab": "0",
    "month": "2026-05",
    "date": "2026 // 05 / 22",
    "ts": 1779418800.0,
    "source_url": "https://ak.hypergryph.com/news/6255",
    "blocks": [
      {
        "type": "text",
        "text": "感谢您对《明日方舟》的关注与支持。《明日方舟》计划将于 2026年05月22日16:00 ~ 16:10 期间进行服务器闪断更新。届时将造成玩家强制掉线，无法登录等问题。为确保您的游戏内账号数据正常，请在本次闪断更新时提前结束关卡。本次更新给各位玩家带来的不便，敬请谅解！"
      },
      {
        "type": "text",
        "text": "闪断更新时间："
      },
      {
        "type": "text",
        "text": "2026年05月22日16:00 ~ 16:10 期间"
      },
      {
        "type": "text",
        "text": "更新内容："
      },
      {
        "type": "text",
        "text": "◆SideStory「众生行记」限时复刻开启，详情请参照官方相关公告"
      },
      {
        "type": "text",
        "text": "◆05月28日04:00【中坚寻访】更新资源预载"
      },
      {
        "type": "text",
        "text": "◆05月28日04:00【采购中心-通用凭证区&高级凭证区】更新（可兑换干员：异客、燧石）资源预载"
      },
      {
        "type": "text",
        "text": "◆修复干员【凯尔希·思衡托】开启技能「破梏重生」部署战术锚点后特殊情况下被击倒表现异常的问题"
      },
      {
        "type": "text",
        "text": "◆修复部分情况下会客室装扮模式保存报错的问题"
      },
      {
        "type": "text",
        "text": "◆修复时装【玛尔特系列 - 硬派速度 - 山】技能「横扫架势」在特定情况下音效缺失的问题"
      },
      {
        "type": "text",
        "text": "◆修复生息演算「重启锚点」中，装置【动力补给站】与部分单位交互时表现异常的问题"
      },
      {
        "type": "text",
        "text": "◆修复生息演算「重启锚点」中，支线篇章【热情熊熊燃烧！】未正确收录到日志的问题"
      },
      {
        "type": "text",
        "text": "◆修复生息演算「重启锚点」中，敌人【冰翼兽】部分情况下未正确变为空中单位的问题"
      },
      {
        "type": "text",
        "text": "◆修复生息演算「重启锚点」中，工艺制材战术倾向返还部分材料错误的问题"
      },
      {
        "type": "text",
        "text": "◆修复生息演算「重启锚点」中，特定情况下装置【清杂机械羽兽】表现异常的问题"
      },
      {
        "type": "text",
        "text": "◆部分文本优化及错误修正"
      },
      {
        "type": "text",
        "text": "◆部分UI优化和修复"
      },
      {
        "type": "text",
        "text": "闪断补偿： 合成玉*200"
      },
      {
        "type": "text",
        "text": "补偿范围： 2026年05月22日16:00更新前所有注册并创建角色的玩家"
      },
      {
        "type": "text",
        "text": "*本次维护不排除延迟开启的可能，如若延迟则请关注官方发布的具体开服时间*"
      },
      {
        "type": "text",
        "text": "【明日方舟】运营组"
      },
      {
        "type": "text",
        "text": "2026年05月22日"
      }
    ]
  },
  {
    "cid": "2823",
    "title": "《明日方舟》制作组通讯#65期",
    "tab": "2",
    "month": "2026-05",
    "date": "2026 // 05 / 18",
    "ts": 1779094800.0,
    "source_url": "https://ak.hypergryph.com/news/2823",
    "blocks": [
      {
        "type": "text",
        "text": "感谢大家一直以来对《明日方舟》的关注与支持，很高兴和大家再次见面。在本期制作组通讯发布之际，生息演算主题【重启锚点】已经开启，欢迎大家体验，同时也再次感谢大家对于主题曲EP17【相变临界】的喜爱与支持。"
      },
      {
        "type": "text",
        "text": "以下，则是本次制作组通讯为大家带来的最新一期的相关活动及版本内容："
      },
      {
        "type": "image",
        "src": "https://raw.githubusercontent.com/Jackie751/report/main/test/%E5%88%B6%E4%BD%9C%E7%BB%84%E9%80%9A%E8%AE%AF/2026___05___18_2823_%E3%80%8A%E6%98%8E%E6%97%A5%E6%96%B9%E8%88%9F%E3%80%8B%E5%88%B6%E4%BD%9C%E7%BB%84%E9%80%9A%E8%AE%AF%2365%E6%9C%9F/01_6c5fddca0e6cc38a19f7c1d272a2a549_41d9a57c.jpg",
        "original_src": "https://web.hycdn.cn/upload/image/20260515/6c5fddca0e6cc38a19f7c1d272a2a549.jpg"
      },
      {
        "type": "text",
        "text": "【通讯节点·一】"
      },
      {
        "type": "text",
        "text": "●梓兰和空爆再次睁开眼，周围的一切都是那么地陌生——"
      },
      {
        "type": "text",
        "text": "泡普卡，斑点，月见夜？为什么你们看起来和平时不太一样？"
      },
      {
        "type": "text",
        "text": "泡影国，诅咒，御轮？罗德岛的数据库中可没有类似的记载。"
      },
      {
        "type": "text",
        "text": "狩猎，异兽，雷之主？天哪，我们真的还能回家吗？"
      },
      {
        "type": "text",
        "text": "带着无尽的疑惑，梓兰和空爆换上新的武器，踏上了属于她们的狩猎之路。"
      },
      {
        "type": "text",
        "text": "●【明日方舟×怪物猎人】SideStory「泡影苍霆」限时活动将于6月上旬开启，该活动包含全新活动关卡与活动剧情，全新联动干员、时装、动态头像、往期时装等联动内容及相关主题家具将伴随本次活动登场及上架，相关签到活动也将同步开启。"
      },
      {
        "type": "text",
        "text": "注意："
      },
      {
        "type": "text",
        "text": "本次活动涉及到可寻访获取的联动干员仅在本次活动的【泡影迷踪干员寻访】开启期间进行获取，不会加入任何【标准寻访】、【中坚寻访】以及【公开招募】。本期卡池详细介绍请见后续相关卡池公告。"
      },
      {
        "type": "image",
        "src": "https://raw.githubusercontent.com/Jackie751/report/main/test/%E5%88%B6%E4%BD%9C%E7%BB%84%E9%80%9A%E8%AE%AF/2026___05___18_2823_%E3%80%8A%E6%98%8E%E6%97%A5%E6%96%B9%E8%88%9F%E3%80%8B%E5%88%B6%E4%BD%9C%E7%BB%84%E9%80%9A%E8%AE%AF%2365%E6%9C%9F/02_9c5dea6753a5984433ae0b00f7e0647f_8a049432.png",
        "original_src": "https://web.hycdn.cn/upload/image/20260513/9c5dea6753a5984433ae0b00f7e0647f.png"
      },
      {
        "type": "text",
        "text": "【通讯节点·二】"
      },
      {
        "type": "text",
        "text": "●「阵地足球锦标」活动将于6月上旬开启，该活动将会是单人的形式，包含晋级赛、淘汰赛和特训赛。此外，该活动还新增了点球玩法，新时装等奖励也可在本次活动中获取。"
      },
      {
        "type": "image",
        "src": "https://raw.githubusercontent.com/Jackie751/report/main/test/%E5%88%B6%E4%BD%9C%E7%BB%84%E9%80%9A%E8%AE%AF/2026___05___18_2823_%E3%80%8A%E6%98%8E%E6%97%A5%E6%96%B9%E8%88%9F%E3%80%8B%E5%88%B6%E4%BD%9C%E7%BB%84%E9%80%9A%E8%AE%AF%2365%E6%9C%9F/03_0980f735e7fc264a073e5031184a1fd1_36bde9cf.png",
        "original_src": "https://web.hycdn.cn/upload/image/20260515/0980f735e7fc264a073e5031184a1fd1.png"
      },
      {
        "type": "text",
        "text": "【通讯节点·三】"
      },
      {
        "type": "text",
        "text": "●【明日方舟×怪物猎人】SideStory「落叶逐火」复刻活动将于6月中旬开启，【砺火成锋】限时寻访将同期进行复刻，该活动同期上架的家具也将限时复刻上架。"
      },
      {
        "type": "text",
        "text": "本次活动涉及到可寻访获取的联动干员仅在本次活动的【狩猎凯旋干员寻访】开启期间进行获取，不会加入任何【标准寻访】、【中坚寻访】以及【公开招募】。本期卡池详细介绍请见后续相关卡池公告；"
      },
      {
        "type": "text",
        "text": "本次复刻活动关卡将继承玩家此前的活动关卡进度及首次掉落进度；"
      },
      {
        "type": "text",
        "text": "本次复刻活动中部分无法重复获得的活动奖励将在重复获得时按照对应比例兑换为【情报凭证】，【情报凭证】兑换比例可参照活动中相应【情报凭证转换规则】；"
      },
      {
        "type": "text",
        "text": "【情报凭证】商店内物品将在活动开启时在原有的商品数量上进行叠加补货及新增其他商品。"
      },
      {
        "type": "image",
        "src": "https://raw.githubusercontent.com/Jackie751/report/main/test/%E5%88%B6%E4%BD%9C%E7%BB%84%E9%80%9A%E8%AE%AF/2026___05___18_2823_%E3%80%8A%E6%98%8E%E6%97%A5%E6%96%B9%E8%88%9F%E3%80%8B%E5%88%B6%E4%BD%9C%E7%BB%84%E9%80%9A%E8%AE%AF%2365%E6%9C%9F/04_cbf5767245cf5143f25fc2d9d8564090_46b6e2a0.png",
        "original_src": "https://web.hycdn.cn/upload/image/20260513/cbf5767245cf5143f25fc2d9d8564090.png"
      },
      {
        "type": "text",
        "text": "【通讯节点·四】"
      },
      {
        "type": "text",
        "text": "●危机合约#5「涤墨作战」将于6月下旬开启，除开放全新的指标及关卡以外，活动中还将加入全新时装、赛季家具等奖励以供获取。同时玩家还可在本次新赛季中完成相关挑战获取对应赛季的蚀刻章。"
      },
      {
        "type": "text",
        "text": "最后，感谢大家阅读本期制作组通讯，以下为本次的制作组通讯奖励："
      },
      {
        "type": "text",
        "text": "奖励内容： 合成玉*200、褐素纤维*5"
      },
      {
        "type": "text",
        "text": "发放时间： 05月18日17:00（邮件领取有效期：7日）"
      },
      {
        "type": "text",
        "text": "发放范围： 05月18日17:00前所有注册并创建角色的玩家"
      },
      {
        "type": "text",
        "text": "*制作组通讯并不代表版本更新及活动最终内容，详细活动计划与版本更新内容等请以届时相关公告为准*"
      },
      {
        "type": "text",
        "text": "《明日方舟》制作组"
      },
      {
        "type": "text",
        "text": "2026年05月18日"
      }
    ]
  },
  {
    "cid": "3044",
    "title": "[活动预告]SideStory「众生行记」复刻即将开启",
    "tab": "1",
    "month": "2026-05",
    "date": "2026 // 05 / 17",
    "ts": 1779008400.0,
    "source_url": "https://ak.hypergryph.com/news/3044",
    "blocks": [
      {
        "type": "image",
        "src": "https://raw.githubusercontent.com/Jackie751/report/main/test/%E6%B4%BB%E5%8A%A8/2026___05___17_3044_%5B%E6%B4%BB%E5%8A%A8%E9%A2%84%E5%91%8A%5DSideStory%E3%80%8C%E4%BC%97%E7%94%9F%E8%A1%8C%E8%AE%B0%E3%80%8D%E5%A4%8D%E5%88%BB%E5%8D%B3%E5%B0%86%E5%BC%80%E5%90%AF/01_c9bb27b88b0a7b3778d1c0dd3ce5a5df_ede0965c.jpg",
        "original_src": "https://web.hycdn.cn/upload/image/20260512/c9bb27b88b0a7b3778d1c0dd3ce5a5df.jpg"
      },
      {
        "type": "text",
        "text": "一、SideStory「众生行记」限时复刻开启"
      },
      {
        "type": "text",
        "text": "活动时间： 05月22日 16:00 - 06月05日 03:59"
      },
      {
        "type": "text",
        "text": "解锁条件： 通关主线1-10"
      },
      {
        "type": "text",
        "text": "活动说明： 活动期间将开放「众生行记」活动关卡，玩家可通过活动关卡作战、制铳师之夜、活动任务及活动商店兑换获取相关活动奖励"
      },
      {
        "type": "text",
        "text": "活动关卡开启时间："
      },
      {
        "type": "text",
        "text": "◆「瞻望圣堂」&「谒见神祇」&「息止安所」： 05月22日 16:00 - 06月01日 03:59"
      },
      {
        "type": "image",
        "src": "https://raw.githubusercontent.com/Jackie751/report/main/test/%E6%B4%BB%E5%8A%A8/2026___05___17_3044_%5B%E6%B4%BB%E5%8A%A8%E9%A2%84%E5%91%8A%5DSideStory%E3%80%8C%E4%BC%97%E7%94%9F%E8%A1%8C%E8%AE%B0%E3%80%8D%E5%A4%8D%E5%88%BB%E5%8D%B3%E5%B0%86%E5%BC%80%E5%90%AF/02_667e1d7abe4133f4c179155df5af4551_eaf72398.jpg",
        "original_src": "https://web.hycdn.cn/upload/image/20260512/667e1d7abe4133f4c179155df5af4551.jpg"
      },
      {
        "type": "text",
        "text": "【制铳师之夜】"
      },
      {
        "type": "text",
        "text": "活动说明： 活动期间，玩家可在【制铳师之夜】完成订单任务获取奖励和每日收益"
      },
      {
        "type": "text",
        "text": "主要奖励： 铳械工坊赠品盒（使用后随机获得指定养成素材）、龙门币、作战记录等"
      },
      {
        "type": "text",
        "text": "◆来到工坊后，每日04:00咖啡壶可调制2杯特浓咖啡。接取订单需要饮用1杯特浓咖啡，工坊解锁后可立即获得2杯特浓咖啡"
      },
      {
        "type": "image",
        "src": "https://raw.githubusercontent.com/Jackie751/report/main/test/%E6%B4%BB%E5%8A%A8/2026___05___17_3044_%5B%E6%B4%BB%E5%8A%A8%E9%A2%84%E5%91%8A%5DSideStory%E3%80%8C%E4%BC%97%E7%94%9F%E8%A1%8C%E8%AE%B0%E3%80%8D%E5%A4%8D%E5%88%BB%E5%8D%B3%E5%B0%86%E5%BC%80%E5%90%AF/03_f6511aa7ff0ff008c19e912569a02a16_ff38554f.jpg",
        "original_src": "https://web.hycdn.cn/upload/image/20260512/f6511aa7ff0ff008c19e912569a02a16.jpg"
      },
      {
        "type": "text",
        "text": "【哄睡指标】"
      },
      {
        "type": "text",
        "text": "活动说明： 活动期间，玩家可通过活动关卡作战完成 【 哄睡指标 】 中相关任务获取奖励"
      },
      {
        "type": "text",
        "text": "主要奖励： 活动干员【★★★★★★：信仰搅拌机】 、 【潘格尼尼的铳械工坊】家具（部分） 、模组养成材料、蒙恩的奶嘴等"
      },
      {
        "type": "text",
        "text": "【甜梦会堂】"
      },
      {
        "type": "text",
        "text": "开放时间： 05月22日 16:00 - 06月05日 03:59"
      },
      {
        "type": "text",
        "text": "兑换说明： 活动期间，玩家可通过活动收集「蒙恩的奶嘴」，消耗「蒙恩的奶嘴」兑换甜梦会堂内物品"
      },
      {
        "type": "text",
        "text": "主要奖励： 【信仰搅拌机】信物 、 【潘格尼尼的铳械工坊】家具（部分） 、 寻访凭证 、高级养成素材、龙门币、作战记录等"
      },
      {
        "type": "text",
        "text": "注意："
      },
      {
        "type": "text",
        "text": "◆本次复刻活动对应蚀刻章套组的相关蚀刻章中，部分蚀刻章的获取条件将进行相应调整，完成相应条件可获取活动对应蚀刻章。由于部分蚀刻章获取条件进行调整，部分已参与过之前活动并满足现蚀刻章获取条件的玩家将在上线时立即获得相应蚀刻章"
      },
      {
        "type": "text",
        "text": "◆本次复刻活动结束后，活动对应蚀刻章套组的相关蚀刻章无法通过【曲谱】或其他任何渠道再次进行获取"
      },
      {
        "type": "text",
        "text": "◆本次复刻活动为轻量化复刻，活动关卡将继承玩家此前的活动关卡进度、首次掉落进度"
      },
      {
        "type": "text",
        "text": "◆本次复刻活动中部分无法重复获得的活动奖励将在重复获得时按照对应比例兑换为【情报凭证】，【情报凭证】兑换比例可参照活动中相应【情报凭证转换规则】"
      },
      {
        "type": "text",
        "text": "◆【情报凭证】商店内物品将在活动开启时在原有的商品数量上进行叠加补货及新增其他商品"
      },
      {
        "type": "text",
        "text": "◆本次活动关卡内【新约能天使】、【蕾缪安】、【信仰搅拌机】、【聆音】、【 CONFESS-47 】信赖获取提升"
      },
      {
        "type": "text",
        "text": "◆本次活动结束后，该活动关卡将于06月05日04:00常驻至【曲谱】"
      },
      {
        "type": "image",
        "src": "https://raw.githubusercontent.com/Jackie751/report/main/test/%E6%B4%BB%E5%8A%A8/2026___05___17_3044_%5B%E6%B4%BB%E5%8A%A8%E9%A2%84%E5%91%8A%5DSideStory%E3%80%8C%E4%BC%97%E7%94%9F%E8%A1%8C%E8%AE%B0%E3%80%8D%E5%A4%8D%E5%88%BB%E5%8D%B3%E5%B0%86%E5%BC%80%E5%90%AF/04_559cc1331127f747876dab0fbcd5371a_c3bac825.jpg",
        "original_src": "https://web.hycdn.cn/upload/image/20260512/559cc1331127f747876dab0fbcd5371a.jpg"
      },
      {
        "type": "text",
        "text": "二、【斗争血脉】系列，新装限时上架"
      },
      {
        "type": "text",
        "text": "活动说明： 活动期间以下干员新增时装将在时装商店上架并限时贩售："
      },
      {
        "type": "text",
        "text": "◆【斗争血脉】系列 - 天穹肇始 - 信仰搅拌机"
      },
      {
        "type": "image",
        "src": "https://raw.githubusercontent.com/Jackie751/report/main/test/%E6%B4%BB%E5%8A%A8/2026___05___17_3044_%5B%E6%B4%BB%E5%8A%A8%E9%A2%84%E5%91%8A%5DSideStory%E3%80%8C%E4%BC%97%E7%94%9F%E8%A1%8C%E8%AE%B0%E3%80%8D%E5%A4%8D%E5%88%BB%E5%8D%B3%E5%B0%86%E5%BC%80%E5%90%AF/05_b8d88bf6d495be8b4fd73ef19eaf4a70_2da34da6.jpg",
        "original_src": "https://web.hycdn.cn/upload/image/20260512/b8d88bf6d495be8b4fd73ef19eaf4a70.jpg"
      },
      {
        "type": "text",
        "text": "三、主题家具限时复刻获取"
      },
      {
        "type": "text",
        "text": "活动说明： 活动期间将限时复刻【“大海的后嗣们”】系列与【潘格尼尼的铳械工坊】系列"
      },
      {
        "type": "text",
        "text": "【“大海的后嗣们”】系列"
      },
      {
        "type": "text",
        "text": "获取方式："
      },
      {
        "type": "text",
        "text": "◆ 家具商店售卖时间：05月22日 16:00 - 06月05日 03:59"
      },
      {
        "type": "image",
        "src": "https://raw.githubusercontent.com/Jackie751/report/main/test/%E6%B4%BB%E5%8A%A8/2026___05___17_3044_%5B%E6%B4%BB%E5%8A%A8%E9%A2%84%E5%91%8A%5DSideStory%E3%80%8C%E4%BC%97%E7%94%9F%E8%A1%8C%E8%AE%B0%E3%80%8D%E5%A4%8D%E5%88%BB%E5%8D%B3%E5%B0%86%E5%BC%80%E5%90%AF/06_919b8744bf7e5801c0204b5eb6888020_5b803e65.jpg",
        "original_src": "https://web.hycdn.cn/upload/image/20260512/919b8744bf7e5801c0204b5eb6888020.jpg"
      },
      {
        "type": "text",
        "text": "【潘格尼尼的铳械工坊】系列"
      },
      {
        "type": "text",
        "text": "◆「众生行记」活动奖励及兑换（部分）"
      },
      {
        "type": "text",
        "text": "◆家具商店限时售卖（部分）"
      },
      {
        "type": "text",
        "text": "更多活动内容请持续关注《明日方舟》游戏内公告及官方公告。"
      },
      {
        "type": "text",
        "text": "【明日方舟】运营组"
      },
      {
        "type": "text",
        "text": "2026年05月17日"
      }
    ]
  },
  {
    "cid": "4935",
    "title": "[明日方舟]05月15日16:00闪断更新公告",
    "tab": "0",
    "month": "2026-05",
    "date": "2026 // 05 / 15",
    "ts": 1778814000.0,
    "source_url": "https://ak.hypergryph.com/news/4935",
    "blocks": [
      {
        "type": "text",
        "text": "感谢您对《明日方舟》的关注与支持。《明日方舟》计划将于 2026年05月15日16:00 ~ 16:10 期间进行服务器闪断更新。届时将造成玩家强制掉线，无法登录等问题。为确保您的游戏内账号数据正常，请在本次闪断更新时提前结束关卡。本次更新给各位玩家带来的不便，敬请谅解！"
      },
      {
        "type": "text",
        "text": "闪断更新时间："
      },
      {
        "type": "text",
        "text": "2026年05月15日16:00 ~ 16:10 期间"
      },
      {
        "type": "text",
        "text": "更新内容："
      },
      {
        "type": "text",
        "text": "◆生息演算主题【重启锚点】开启，详情请参照官方相关公告及自媒体相关内容"
      },
      {
        "type": "text",
        "text": "◆【定向甄选】限时寻访开启"
      },
      {
        "type": "text",
        "text": "◆曲谱故事线中SideStory「人们，我们」故事关系更新"
      },
      {
        "type": "text",
        "text": "◆05月16日04:00【保全派驻】奖励进度更新资源预载"
      },
      {
        "type": "text",
        "text": "◆05月21日04:00常驻【标准寻访】更新资源预载"
      },
      {
        "type": "text",
        "text": "◆05月21日04:00【采购中心-高级凭证区】更新（可兑换干员：圣约送葬人、海霓）资源预载"
      },
      {
        "type": "text",
        "text": "◆修复主题曲「相变临界」关卡【H17-4】中部分地块错误的问题"
      },
      {
        "type": "text",
        "text": "◆修复干员【可露希尔】技能「Q.E.D.」在特定情况下攻击表现异常的问题"
      },
      {
        "type": "text",
        "text": "◆修复干员【浊心斯卡蒂】携带3级专属模组【新生代】时，天赋「捕食习性」效果异常的问题"
      },
      {
        "type": "text",
        "text": "◆部分UI优化和修复"
      },
      {
        "type": "text",
        "text": "◆部分文本优化及错误修正"
      },
      {
        "type": "text",
        "text": "闪断补偿： 合成玉*200"
      },
      {
        "type": "text",
        "text": "补偿范围： 2026年05月15日16:00更新前所有注册并创建角色的玩家"
      },
      {
        "type": "text",
        "text": "*本次维护不排除延迟开启的可能，如若延迟则请关注官方发布的具体开服时间*"
      },
      {
        "type": "text",
        "text": "【明日方舟】运营组"
      },
      {
        "type": "text",
        "text": "2026年05月15日"
      }
    ]
  },
  {
    "cid": "4936",
    "title": "[明日方舟]05月08日16:00闪断更新公告",
    "tab": "0",
    "month": "2026-05",
    "date": "2026 // 05 / 08",
    "ts": 1778209200.0,
    "source_url": "https://ak.hypergryph.com/news/4936",
    "blocks": [
      {
        "type": "text",
        "text": "感谢您对《明日方舟》的关注与支持。《明日方舟》计划将于 2026年05月08日16:00 ~ 16:10 期间进行服务器闪断更新。届时将造成玩家强制掉线，无法登录等问题。为确保您的游戏内账号数据正常，请在本次闪断更新时提前结束关卡。本次更新给各位玩家带来的不便，敬请谅解！"
      },
      {
        "type": "text",
        "text": "闪断更新时间："
      },
      {
        "type": "text",
        "text": "2026年05月08日16:00 ~ 16:10 期间"
      },
      {
        "type": "text",
        "text": "更新内容："
      },
      {
        "type": "text",
        "text": "◆主题曲【相变临界】绝境作战关卡开放（通过沙盘推演积累指定推演分数后解锁）"
      },
      {
        "type": "text",
        "text": "◆05月14日04:00【中坚甄选】更新资源预载"
      },
      {
        "type": "text",
        "text": "◆05月14日04:00【采购中心-通用凭证区&高级凭证区】更新资源预载"
      },
      {
        "type": "text",
        "text": "◆修复干员【异客】携带2、3级专属模组【异客特限证章】时，天赋「机理分析」在特定潜能下效果异常的问题"
      },
      {
        "type": "text",
        "text": "◆修复主题曲「相变临界」关卡【17-17】沙盘推演假设生效异常的问题"
      },
      {
        "type": "text",
        "text": "◆修复【修道院居民】在特定情况下恐慌后表现异常的问题"
      },
      {
        "type": "text",
        "text": "◆修复敌人【“终始”】特定情况下完成指定交互表现异常的问题"
      },
      {
        "type": "text",
        "text": "◆修复干员【凯尔希·思衡托】技能「破梏重生」和树丛交互异常的问题"
      },
      {
        "type": "text",
        "text": "◆修复干员【凯尔希·思衡托】天赋「医者丰碑」部分情况下效果异常的问题"
      },
      {
        "type": "text",
        "text": "◆修复干员【斩业星熊】部分情况下进入“我执”状态时错误成为治疗目标的问题"
      },
      {
        "type": "text",
        "text": "◆部分文本优化及错误修正"
      },
      {
        "type": "text",
        "text": "◆部分UI美术切图特效优化和修复"
      },
      {
        "type": "text",
        "text": "闪断补偿： 合成玉*200"
      },
      {
        "type": "text",
        "text": "补偿范围： 2026年05月08日16:00更新前所有注册并创建角色的玩家"
      },
      {
        "type": "text",
        "text": "*本次维护不排除延迟开启的可能，如若延迟则请关注官方发布的具体开服时间*"
      },
      {
        "type": "text",
        "text": "【明日方舟】运营组"
      },
      {
        "type": "text",
        "text": "2026年05月08日"
      }
    ]
  },
  {
    "cid": "3045",
    "title": "[明日方舟]05月01日23:50闪断更新公告",
    "tab": "0",
    "month": "2026-05",
    "date": "2026 // 05 / 01",
    "ts": 1777643400.0,
    "source_url": "https://ak.hypergryph.com/news/3045",
    "blocks": [
      {
        "type": "text",
        "text": "感谢您对《明日方舟》的关注与支持。《明日方舟》计划将于 2026年05月01日23:50 ~ 24:00 期间进行服务器闪断更新。届时将造成玩家强制掉线，无法登录等问题。为确保您的游戏内账号数据正常，请在本次闪断更新时提前结束关卡。本次更新给各位玩家带来的不便，敬请谅解！"
      },
      {
        "type": "text",
        "text": "闪断更新时间："
      },
      {
        "type": "text",
        "text": "2026年05月01日23:50 ~ 24:00 期间"
      },
      {
        "type": "text",
        "text": "更新内容："
      },
      {
        "type": "text",
        "text": "◆修复集成战略【岁的界园志异】中，装置【明烛台】生效异常导致卡死的问题"
      },
      {
        "type": "text",
        "text": "◆修复干员【浊心斯卡蒂】模组解锁任务计数异常的问题"
      },
      {
        "type": "text",
        "text": "◆修复干员【可露希尔】技能「模型扩展」特定情况下在战术点效果范围内部署干员时部署费用返还异常的问题"
      },
      {
        "type": "text",
        "text": "◆部分文本优化及错误修正"
      },
      {
        "type": "text",
        "text": "◆部分UI优化和修复"
      },
      {
        "type": "text",
        "text": "闪断补偿： 合成玉*200"
      },
      {
        "type": "text",
        "text": "补偿范围： 2026年05月01日23:50更新前所有注册并创建角色的玩家"
      },
      {
        "type": "text",
        "text": "*本次维护不排除延迟开启的可能，如若延迟则请关注官方发布的具体开服时间*"
      },
      {
        "type": "text",
        "text": "【明日方舟】运营组"
      },
      {
        "type": "text",
        "text": "2026年05月01日"
      }
    ]
  },
  {
    "cid": "0703",
    "title": "「相变临界」创作征集活动",
    "tab": "1",
    "month": "2026-05",
    "date": "2026 // 05 / 01",
    "ts": 1777608000.0,
    "source_url": "https://ak.hypergryph.com/news/0703",
    "blocks": [
      {
        "type": "image",
        "src": "https://raw.githubusercontent.com/Jackie751/report/main/test/%E6%B4%BB%E5%8A%A8/2026___05___01_0703_%E3%80%8C%E7%9B%B8%E5%8F%98%E4%B8%B4%E7%95%8C%E3%80%8D%E5%88%9B%E4%BD%9C%E5%BE%81%E9%9B%86%E6%B4%BB%E5%8A%A8/01_a51c3f1d4444c5a01c09c44906d298b2_29babd4d.jpg",
        "original_src": "https://web.hycdn.cn/upload/image/20260430/a51c3f1d4444c5a01c09c44906d298b2.jpg"
      },
      {
        "type": "text",
        "text": "「相变临界」创作征集进行中"
      },
      {
        "type": "text",
        "text": "《明日方舟》「相变临界」创作征集活动现已在多平台进行中。各位博士可在 哔哩哔哩、抖音、微博、小红书、快手、微信游戏圈、QQ频道 等平台按活动要求进行内容创作，即可参与创作瓜分、作品评优、互动抽奖等活动并赢取现金、游戏内道具和实物周边等丰厚奖励！"
      },
      {
        "type": "text",
        "text": "◆ 哔哩哔哩"
      },
      {
        "type": "text",
        "text": "即日起至活动结束，在哔哩哔哩平台带话题 #明日方舟创作者应援计划 进行视频投稿，或在《明日方舟》分区进行直播，达到规定条件即可参与现金瓜分，更有机会获得优秀稿件或主播评优奖励。"
      },
      {
        "type": "text",
        "text": "活动结束时间：2026年5月31日23:59"
      },
      {
        "type": "text",
        "text": "点击跳转活动页面"
      },
      {
        "type": "text",
        "text": "◆ 抖音"
      },
      {
        "type": "text",
        "text": "即日起至活动结束，在抖音平台带话题 #明日方舟 、 #明日方舟七周年 ，并挂载《明日方舟》小手柄进行投稿，或挂载小手柄直播《明日方舟》游戏内容，达到条件可参与作者榜单、现金瓜分等活动。同时，您可通过观看活动投稿、直播等完成互动抽奖任务，有机会获得游戏礼包、游戏周边等丰厚奖励。"
      },
      {
        "type": "text",
        "text": "◆ 微博"
      },
      {
        "type": "text",
        "text": "即日起至活动结束，在微博超话带话题 #明日方舟七周年# 、 #明日方舟创作征集# 进行原创投稿，即可参与创作征集活动，有机会获得 现金、 角色手办、游戏周边等奖励。"
      },
      {
        "type": "text",
        "text": "点击跳转活动详情"
      },
      {
        "type": "text",
        "text": "◆ 小红书"
      },
      {
        "type": "text",
        "text": "即日起至活动结束，在小红书平台带话题 #明日方舟 、 #明日方舟七周年 及其他赛道话题进行笔记发布，即可参与现金瓜分与优秀作者评优，获得现金及游戏周边等奖励。同时，您也可通过发布、点赞、评论活动笔记等方式完成互动任务参与抽奖，有机会获得游戏礼包、游戏周边等奖励。"
      },
      {
        "type": "text",
        "text": "◆ 快手"
      },
      {
        "type": "text",
        "text": "即日起至活动结束，在快手平台带话题 #明日方舟 、 #明日方舟七周年 进行投稿，即可参与投稿瓜分与优秀作者评选。同时，您也可通过关注明日方舟快手官号、发布、点赞、评论活动投稿等方式完成互动任务参与抽奖，有机会获得游戏礼包、游戏周边等奖励。"
      },
      {
        "type": "text",
        "text": "◆ 微信游戏圈"
      },
      {
        "type": "text",
        "text": "即日起至活动结束，在微信游戏圈 #明日方舟七周年# 话题内参与版本福利、话题讨论、每日签到等活动，完成指定任务即有机会获得实物周边、游戏礼包等奖励。"
      },
      {
        "type": "text",
        "text": "活动结束时间：具体可在【明日方舟游戏圈】活动页面查看"
      },
      {
        "type": "text",
        "text": "◆ QQ频道"
      },
      {
        "type": "text",
        "text": "即日起至活动结束，加入明日方舟官方频道，在子频道 「七周年」 中参与活动投稿，或参与版本福利活动，完成指定任务即有机会获得实物周边、游戏礼包等奖励。"
      },
      {
        "type": "text",
        "text": "更多活动赛道与参与规则等信息，可关注对应社区平台发布。"
      },
      {
        "type": "text",
        "text": "我们将持续努力为创作者带来更优质的创作体验，感谢各位博士对《明日方舟》的支持。"
      }
    ]
  },
  {
    "cid": "9692",
    "title": "[明日方舟]05月01日06:00版本更新停机维护公告",
    "tab": "0",
    "month": "2026-04",
    "date": "2026 // 04 / 30",
    "ts": 1777539600.0,
    "source_url": "https://ak.hypergryph.com/news/9692",
    "blocks": [
      {
        "type": "text",
        "text": "感谢您对《明日方舟》的关注与支持，《明日方舟》计划将于2026年05月01日06:00至12:00对客户端进行版本更新停机维护。 本次更新为强制更新，更新结束后，需玩家对游戏客户端进行重新下载和安装。"
      },
      {
        "type": "text",
        "text": "更新维护期间玩家将无法登录游戏，更新结束后玩家将无法登录当前版本继续进行游戏。为确保您的账号数据正常，请在维护前提前结束关卡，并关闭游戏。 给各位玩家带来的不便，我们深表歉意！还请各位玩家相互转告。"
      },
      {
        "type": "text",
        "text": "维护时间："
      },
      {
        "type": "text",
        "text": "2026年05月01日06:00 ~ 12:00"
      },
      {
        "type": "text",
        "text": "更新说明："
      },
      {
        "type": "text",
        "text": "◆移动端：游戏客户端版本强制更新， 更新结束后，需玩家对游戏客户端进行重新下载和安装"
      },
      {
        "type": "text",
        "text": "◆PC端：使用鹰角启动器进行游戏更新"
      },
      {
        "type": "text",
        "text": "注意："
      },
      {
        "type": "text",
        "text": "维护后的开服时间存在提前或延迟的可能，详情请关注官方公告"
      },
      {
        "type": "text",
        "text": "更新内容："
      },
      {
        "type": "text",
        "text": "【活动】"
      },
      {
        "type": "text",
        "text": "◆「七周年庆典」限时活动 Part.1开启，活动详情请参照官方相关公告"
      },
      {
        "type": "text",
        "text": "【内容】"
      },
      {
        "type": "text",
        "text": "◆新增以下干员的【干员密录】："
      },
      {
        "type": "text",
        "text": "【可露希尔】、【怒潮凛冬】、【亚叶】、【哈蒂娅】"
      },
      {
        "type": "text",
        "text": "◆新增以下干员的【悖论模拟】："
      },
      {
        "type": "text",
        "text": "【亚叶】、【哈蒂娅】、【阿兰娜】"
      },
      {
        "type": "text",
        "text": "◆新增以下干员的【专属模组】："
      },
      {
        "type": "text",
        "text": "【锏】（第二件）、【信仰搅拌机】（第二件）、【缄默德克萨斯】（第二件）、【可露希尔】、【维伊】、【裂响】"
      },
      {
        "type": "text",
        "text": "◆新增以下干员的【特限模组】："
      },
      {
        "type": "text",
        "text": "【归溟幽灵鲨】、【提丰】"
      },
      {
        "type": "text",
        "text": "◆新增以下干员及时装的英文语音："
      },
      {
        "type": "text",
        "text": "【凛御银灰】、【圣聆初雪】、【溯光星源】、【真言】、【折桠】、【雪猎】、【哈蒂娅】、【冬时】、【协律】、时装【忒斯特收藏系列 - 无序的谦卑 - 荒芜拉普兰德】、时装【时代系列 - 追悼 - 魔王】"
      },
      {
        "type": "text",
        "text": "◆新增以下干员及时装的韩文语音："
      },
      {
        "type": "text",
        "text": "◆新增以下干员的个性化语音（意大利语）："
      },
      {
        "type": "text",
        "text": "【贝洛内】"
      },
      {
        "type": "text",
        "text": "◆理智上限提升，累计签到系统更新，详情请参照官方相关公告"
      },
      {
        "type": "text",
        "text": "◆【采购凭证商店】可兑换内容更新，详情请参照官方相关公告"
      },
      {
        "type": "text",
        "text": "◆光荣之路新增部分蚀刻章"
      },
      {
        "type": "text",
        "text": "◆术语释义新增“迟钝”、“部署费用下限”、“可露希尔特别订单”相关内容"
      },
      {
        "type": "text",
        "text": "◆干员【初雪】、【截云】、【仇白】韩文语音更新"
      },
      {
        "type": "text",
        "text": "◆主题曲「相变临界」的活动商店将加入新的无限兑换材料【RMA70-12】"
      },
      {
        "type": "text",
        "text": "◆05月07日04:00常驻【标准寻访】更新资源预载"
      },
      {
        "type": "text",
        "text": "◆05月07日04:00【采购中心-高级凭证区】更新（可兑换干员：左乐、杏仁）资源预载"
      },
      {
        "type": "text",
        "text": "【战斗】"
      },
      {
        "type": "text",
        "text": "◆修复【争锋频道：绿藤城】中部分敌人交互异常的问题"
      },
      {
        "type": "text",
        "text": "◆修复干员【阿罗玛】技能「强效清洁」在特定情况下特效显示异常的问题"
      },
      {
        "type": "text",
        "text": "◆修复时装【音律联觉系列 - 晶化信念 - 死芒】技能「冠死以冕」在特定情况下特效显示异常的问题"
      },
      {
        "type": "text",
        "text": "【其他】"
      },
      {
        "type": "text",
        "text": "◆修复名片主题【布道人】、【戏中身】、【渡星客】、【失语者】特效显示异常的问题"
      },
      {
        "type": "text",
        "text": "◆修复时装【音律联觉系列 - 晶化信念 - 死芒】美术资源清晰度异常问题"
      },
      {
        "type": "text",
        "text": "◆部分UI美术切图优化和修复"
      },
      {
        "type": "text",
        "text": "◆部分文本优化及错误修正"
      },
      {
        "type": "text",
        "text": "强制更新补偿： 至纯源石*5"
      },
      {
        "type": "text",
        "text": "补偿范围： 2026年05月01日06:00更新前所有注册并创建角色的玩家"
      },
      {
        "type": "text",
        "text": "领取时间： 本次维护结束后的7日内"
      },
      {
        "type": "text",
        "text": "*本次维护不排除提前或延迟开启的可能，详情请关注官方公告*"
      },
      {
        "type": "text",
        "text": "【明日方舟】运营组"
      },
      {
        "type": "text",
        "text": "2026年04月30日"
      }
    ]
  },
  {
    "cid": "6251",
    "title": "《明日方舟》制作组通讯#63期",
    "tab": "2",
    "month": "2026-03",
    "date": "2026 // 03 / 24",
    "ts": 1774342800.0,
    "source_url": "https://ak.hypergryph.com/news/6251",
    "blocks": [
      {
        "type": "text",
        "text": "感谢大家一直以来对《明日方舟》的关注与支持，很高兴和大家再次见面。在本期制作组通讯发布之际，「卫戍协议：盟约」限时活动已经开启了一段时间，欢迎大家体验，同时也再次感谢大家对于此前故事集「十字路口」的喜爱与支持。"
      },
      {
        "type": "text",
        "text": "以下，则是本次制作组通讯为大家带来的最新一期的相关活动及版本内容："
      },
      {
        "type": "image",
        "src": "https://raw.githubusercontent.com/Jackie751/report/main/test/%E5%88%B6%E4%BD%9C%E7%BB%84%E9%80%9A%E8%AE%AF/2026___03___24_6251_%E3%80%8A%E6%98%8E%E6%97%A5%E6%96%B9%E8%88%9F%E3%80%8B%E5%88%B6%E4%BD%9C%E7%BB%84%E9%80%9A%E8%AE%AF%2363%E6%9C%9F/01_e950fed647c379611f51ffdffaacc4df_89113476.jpg",
        "original_src": "https://web.hycdn.cn/upload/image/20260319/e950fed647c379611f51ffdffaacc4df.jpg"
      },
      {
        "type": "text",
        "text": "【通讯节点·一】"
      },
      {
        "type": "text",
        "text": "●圣骏堡阴郁的天幕下，他们曾谈论着明天，"
      },
      {
        "type": "text",
        "text": "直到伟大的城市也被划为牢笼，扼死了所有幻想。"
      },
      {
        "type": "text",
        "text": "乌萨斯不会听到，那些精妙的修辞，和喑哑的哭号。"
      },
      {
        "type": "text",
        "text": "暴虐、阴谋、蔑视......回敬这些的，只有汹涌的怒火。"
      },
      {
        "type": "text",
        "text": "你在哪里，雷霆——我听见自由的灵魂，那声嘶力竭的咆哮。"
      },
      {
        "type": "text",
        "text": "●SideStory「人们，我们」限时活动将于4月上旬开启，该活动除包含全新活动关卡与剧情外，新干员和新时装以及相关主题家具也将伴随本次活动登场及上架。"
      },
      {
        "type": "text",
        "text": "最后，感谢大家阅读本期制作组通讯，以下为本次的制作组通讯奖励："
      },
      {
        "type": "text",
        "text": "奖励内容： 合成玉*200、化合切削液*5"
      },
      {
        "type": "text",
        "text": "发放时间： 03月24日17:00（邮件领取有效期：7日）"
      },
      {
        "type": "text",
        "text": "发放范围： 03月24日17:00前所有注册并创建角色的玩家"
      },
      {
        "type": "text",
        "text": "*制作组通讯并不代表版本更新及活动最终内容，详细活动计划与版本更新内容等请以届时相关公告为准*"
      },
      {
        "type": "text",
        "text": "《明日方舟》制作组"
      },
      {
        "type": "text",
        "text": "2026年03月24日"
      }
    ]
  },
  {
    "cid": "5114",
    "title": "[明日方舟]「卫戍协议：盟约」更新公告",
    "tab": "1",
    "month": "2026-03",
    "date": "2026 // 03 / 14",
    "ts": 1773459000.0,
    "source_url": "https://ak.hypergryph.com/news/5114",
    "blocks": [
      {
        "type": "text",
        "text": "感谢大家对《明日方舟》的关注与支持。"
      },
      {
        "type": "text",
        "text": "「卫戍协议：盟约」下半期活动将于03月14日16:00 ~ 17:00的停机维护后开启，此次活动在优化系统的同时更新了活动内容，具体内容如下："
      },
      {
        "type": "text",
        "text": "（一）系统优化及新增内容"
      },
      {
        "type": "text",
        "text": "◆系统优化："
      },
      {
        "type": "text",
        "text": "-独立模拟： 休整期及机变阶段的持续时间无限，博士可以在任意回合和阶段中暂时离开 ，并可在 24小时 内随时返回，暂时离开后，博士可以点击【放弃模拟】直接进行本次模拟结算；此外，完成【标准模拟】所需的回合数也将减少"
      },
      {
        "type": "text",
        "text": "-同盟模拟： 取消勾选【房间未满4人时搜寻队友】时，即可以少于4人的盟友数直接开启同盟模拟 ；同时，独立模拟与同盟模拟的模拟协议解锁状态将互通，二者都将新增更具挑战性的模拟协议【终极模拟】"
      },
      {
        "type": "text",
        "text": "-预设干员： 所有的4、5星及活动赠送6星干员都无需调用，未持有该干员也可以在活动中直接调用"
      },
      {
        "type": "text",
        "text": "-交互体验： 装备可直接配置在处于整备区的干员身上 ，同时，整备区已满时仍可将整备区的干员与战场区的干员进行位置交换"
      },
      {
        "type": "text",
        "text": "-按键适配：《明日方舟》PC端将上线「卫戍协议：盟约」 专属的按键适配功能"
      },
      {
        "type": "text",
        "text": "-敌人：在联合模拟的最终攻势阶段， 部分敌方领袖会同时出现在战场的左右两侧 ，两侧的敌方领袖共享生命值（敌方领袖的总生命值不变）；此外，敌人【灼藤】与【元核孽生者】的攻击力也将降低"
      },
      {
        "type": "text",
        "text": "◆新增内容："
      },
      {
        "type": "text",
        "text": "-新增核心盟约：【叙拉古】、【卡西米尔】，新增附加盟约：【绝技】、【奥术】、【独行】，详情请参照官方自媒体相关介绍"
      },
      {
        "type": "text",
        "text": "-新增策略：【巫恋】、【伊奥莱塔·罗素】、【松桐】、【玛恩纳】、【贾维】、【娜仁图亚】、【Touch】，后续还将开放数个新增策略，详情请参照官方自媒体相关介绍"
      },
      {
        "type": "text",
        "text": "-新增部分预设干员，暂离部分「卫戍协议：盟约」上半期预设干员，详情请参照官方自媒体相关介绍"
      },
      {
        "type": "text",
        "text": "-新增装备：【简易通讯机】、【紧急调度券】、【天马之枪】、【天马之盔】、【卡西米尔竞技旗】、【骑士戒律】、【叙拉古正装】、【家族徽章】、【骑士储蓄罐】、【盟约之币】，详情请参照官方自媒体及游戏内介绍"
      },
      {
        "type": "text",
        "text": "-新增全新表情、地图与敌人"
      },
      {
        "type": "text",
        "text": "（二）活动内容调整"
      },
      {
        "type": "text",
        "text": "◆盟约调整："
      },
      {
        "type": "text",
        "text": "-盟约【炎】，召唤物【“炎佑”】的攻击目标数提升，“祛恶之焰”附带的灼燃损伤调整为基于【“炎佑”】的攻击力，新增效果：<在场9名不同【炎】干员>时召唤2只【“炎佑”】，攻击力提升，受到的伤害减少"
      },
      {
        "type": "text",
        "text": "-盟约【维多利亚】，<在场6名不同【维多利亚】干员>新增效果：干员携带进阶装备时攻击力额外提升"
      },
      {
        "type": "text",
        "text": "-盟约【阿戈尔】，修复联防阶段部分情况下因干员处于被击倒状态无法吞噬获得攻击力的问题，<在场5名不同【阿戈尔】干员>的效果中特定数量【阿戈尔】干员首次被击倒时立刻复活的数量提升至前3名"
      },
      {
        "type": "text",
        "text": "-盟约【远见】，新增叠加至指定层数时【远见】干员的购买价格永久降低的效果，所有干员购买价格降低的效果所需层数调整"
      },
      {
        "type": "text",
        "text": "-盟约【精准】，激活效果调整为【精准】干员攻击力提升，<在场3名不同【精准】干员>效果调整为:【精准】干员和所有远程干员攻击力提升，且攻击无视一定的防御力和法术抗性"
      },
      {
        "type": "text",
        "text": "-盟约【坚守】，<在场3名不同【坚守】干员>新增效果：【坚守】干员受到伤害时，伤害来源将受到一定法术伤害和持续一定时间的脆弱效果"
      },
      {
        "type": "text",
        "text": "-盟约【突袭】，新增再部署判定条件：干员一定时间内未进行攻击，<达到50层>效果调整为所有干员攻击速度增加"
      },
      {
        "type": "text",
        "text": "-盟约【协防干员】，激活所需人数减少，盟约效果调整为所有干员受到的物理和法术伤害减少，【协防干员】伤害提升，精锐【协防干员】造成伤害提升至更高"
      },
      {
        "type": "text",
        "text": "-盟约【迅捷】，激活效果中【迅捷】干员技能结束时有概率立刻回复的技力增加"
      },
      {
        "type": "text",
        "text": "-盟约【灵巧】，激活效果中【灵巧】干员的攻击速度提升效果范围调整，<达到40层>的效果调整为攻击速度提升效果范围扩大"
      },
      {
        "type": "text",
        "text": "◆策略调整："
      },
      {
        "type": "text",
        "text": "-夕策略新增【墨色真颜】效果，若场上存在同名干员，这些干员攻击力提升"
      },
      {
        "type": "text",
        "text": "-阿米娅策略的【众志合一】效果调整为场上存在3、4或5种以上激活盟约时，所有干员攻击力、生命值分别增加一定百分比"
      },
      {
        "type": "text",
        "text": "-大帝策略的【加急调派】效果描述调整，实际效果不变"
      },
      {
        "type": "text",
        "text": "-桑葚策略的【药枚实验】效果，提升最右边的所有我方单位每次攻击时获得护盾的概率"
      },
      {
        "type": "text",
        "text": "-“变形者集群”策略的【变形同构】效果调整为每5回合获得1件特殊装备<变形同构体>"
      },
      {
        "type": "text",
        "text": "-埃芒加德策略的【命结之秘】效果，战斗中前一定数量被击倒的干员立刻复活提升至前3个"
      },
      {
        "type": "text",
        "text": "-余策略的【文火慢炖】效果，第8回合开始时若仅激活了1个盟约，使其增加的层数调整"
      },
      {
        "type": "text",
        "text": "◆预设干员调整："
      },
      {
        "type": "text",
        "text": "-调整部分「卫戍协议：盟约」上半期预设干员的等阶、特质及所属盟约，详情请参照游戏内介绍"
      },
      {
        "type": "text",
        "text": "◆装备调整："
      },
      {
        "type": "text",
        "text": "-装备【商业包装方案】，效果调整为：每出售7名干员，额外获得一个此装备携带者的同盟约初始干员（不高于当前调度中心等级）"
      },
      {
        "type": "text",
        "text": "-装备【海沟实验体】，携带者为【阿戈尔】盟约干员的效果调整为：该干员受到伤害时对伤害来源造成自身攻击力一定百分比的法术伤害，若该干员同时装备【阿戈尔重刃】，则额外造成一次攻击力一定百分比的法术伤害"
      },
      {
        "type": "text",
        "text": "-装备【耶拉冈德之泪】，携带者为【谢拉格】盟约干员的效果调整为：该干员攻击范围内被寒冷或冻结的敌人每秒受到一次自身攻击力一定百分比的法术伤害，若该干员同时装备【谢拉格不融冰】，则使自身攻击范围内寒冷或被冻结的敌人每秒受到的法术伤害提升至更高百分比的攻击力"
      },
      {
        "type": "text",
        "text": "-装备【寻呼模块】，效果调整为：装备时销毁，立即特殊刷新一次调度中心，出现三名与该干员有相同盟约的不同干员，免费获取其中一名（不高于当前调度中心等级）"
      },
      {
        "type": "text",
        "text": "-装备【信标】，新增效果：装备时，目标干员和本装备销毁并进行一次特殊刷新，出现两名与携带者同等阶的干员，免费获取其中一名"
      },
      {
        "type": "text",
        "text": "再次感谢大家对于《明日方舟》的喜爱与支持，未来我们将持续关注大家的游戏体验并优化游戏内容，更多活动内容请持续关注《明日方舟》游戏内公告及官方公告。"
      },
      {
        "type": "text",
        "text": "【明日方舟】运营组"
      },
      {
        "type": "text",
        "text": "2026年03月14日"
      }
    ]
  },
  {
    "cid": "9697",
    "title": "[活动预告] 「卫戍协议：盟约」限时活动即将开启",
    "tab": "1",
    "month": "2026-03",
    "date": "2026 // 03 / 11",
    "ts": 1773198000.0,
    "source_url": "https://ak.hypergryph.com/news/9697",
    "blocks": [
      {
        "type": "image",
        "src": "https://raw.githubusercontent.com/Jackie751/report/main/test/%E6%B4%BB%E5%8A%A8/2026___03___11_9697_%5B%E6%B4%BB%E5%8A%A8%E9%A2%84%E5%91%8A%5D_%E3%80%8C%E5%8D%AB%E6%88%8D%E5%8D%8F%E8%AE%AE%EF%BC%9A%E7%9B%9F%E7%BA%A6%E3%80%8D%E9%99%90%E6%97%B6%E6%B4%BB%E5%8A%A8%E5%8D%B3%E5%B0%86%E5%BC%80%E5%90%AF/01_961aa6264167bc8669179e12e2397daa_7ba96828.jpg",
        "original_src": "https://web.hycdn.cn/upload/image/20260310/961aa6264167bc8669179e12e2397daa.jpg"
      },
      {
        "type": "text",
        "text": "一、「卫戍协议：盟约」限时活动开启"
      },
      {
        "type": "text",
        "text": "关卡开放时间： 03月14日 16:00 - 04月25日 03:59"
      },
      {
        "type": "text",
        "text": "解锁条件： 通关主线1-10"
      },
      {
        "type": "text",
        "text": "活动说明： 「卫戍协议：盟约」下半期活动开启，玩家可通过活动关卡作战、完成关键目标及每日防卫目标获取【卫戍认证】，提升【功勋兑换处】等级获取相应活动奖励；本期活动优化了独立模拟与联合模拟的体验，还将包含新难度、新盟约、新策略等多种新内容"
      },
      {
        "type": "text",
        "text": "【功勋兑换处】开放时间： 03月14日 16:00 - 04月28日 03:59"
      },
      {
        "type": "text",
        "text": "【功勋兑换处】主要奖励： 时装 【玛尔特系列 -  补水时间  - 慕斯】 、 活动头像 、模组养成材料、高级养成素材、作战记录、龙门币等"
      },
      {
        "type": "text",
        "text": "◆ 03月14日16:00 - 17:00将开启服务器停机维护，「卫戍协议：盟约」将在维护后开启 ，活动开启时间存在提前或延迟的可能，详情请关注后续公告"
      },
      {
        "type": "text",
        "text": "◆「卫戍协议：盟约」专属的按键适配功能将于活动开启后在《明日方舟》PC端上线"
      },
      {
        "type": "text",
        "text": "◆每日防卫目标：玩家每日通过模拟累积获得指定数量的【卫戍认证】，即可在结算时领取额外的【卫戍认证】奖励，该奖励每天可领取一次，每天凌晨04:00重置"
      },
      {
        "type": "text",
        "text": "◆部分往期时装将在03月14日 16:00 - 04月04日 03:59复刻上架，详情请参照游戏内时装商店"
      },
      {
        "type": "text",
        "text": "◆详细活动玩法介绍请关注后续官方自媒体相关内容"
      },
      {
        "type": "image",
        "src": "https://raw.githubusercontent.com/Jackie751/report/main/test/%E6%B4%BB%E5%8A%A8/2026___03___11_9697_%5B%E6%B4%BB%E5%8A%A8%E9%A2%84%E5%91%8A%5D_%E3%80%8C%E5%8D%AB%E6%88%8D%E5%8D%8F%E8%AE%AE%EF%BC%9A%E7%9B%9F%E7%BA%A6%E3%80%8D%E9%99%90%E6%97%B6%E6%B4%BB%E5%8A%A8%E5%8D%B3%E5%B0%86%E5%BC%80%E5%90%AF/02_f42180d055374121367a74d0e6b11eb4_3fc49550.jpg",
        "original_src": "https://web.hycdn.cn/upload/image/20260310/f42180d055374121367a74d0e6b11eb4.jpg"
      },
      {
        "type": "text",
        "text": "二、【联合行动】特选干员定向寻访开启"
      },
      {
        "type": "text",
        "text": "活动时间： 03月14日 16:00 - 03月28日 03:59"
      },
      {
        "type": "text",
        "text": "活动说明： 活动期间【联合行动】特选干员定向寻访开启，该寻访卡池列表中六星干员与五星干员仅出现以下干员"
      },
      {
        "type": "text",
        "text": "★★★★★★（6★出率：2%）：真言 / 忍冬 / 妮芙 / 乌尔比安"
      },
      {
        "type": "text",
        "text": "★★★★★（5★出率：8%）：响石 / 子月 / 和弦 / 温米 / 寻澜 / 波卜"
      },
      {
        "type": "text",
        "text": "注意： 本次活动【联合行动】寻访为【标准寻访】"
      },
      {
        "type": "image",
        "src": "https://raw.githubusercontent.com/Jackie751/report/main/test/%E6%B4%BB%E5%8A%A8/2026___03___11_9697_%5B%E6%B4%BB%E5%8A%A8%E9%A2%84%E5%91%8A%5D_%E3%80%8C%E5%8D%AB%E6%88%8D%E5%8D%8F%E8%AE%AE%EF%BC%9A%E7%9B%9F%E7%BA%A6%E3%80%8D%E9%99%90%E6%97%B6%E6%B4%BB%E5%8A%A8%E5%8D%B3%E5%B0%86%E5%BC%80%E5%90%AF/03_9d45752fa36d727fcecfadd5032f5b48_42baf140.jpg",
        "original_src": "https://web.hycdn.cn/upload/image/20260310/9d45752fa36d727fcecfadd5032f5b48.jpg"
      },
      {
        "type": "text",
        "text": "三、组合包限时上架"
      },
      {
        "type": "text",
        "text": "活动说明： 活动期间，采购中心将限时售卖以下组合包"
      },
      {
        "type": "text",
        "text": "售卖时间： 03月14日 16:00 - 04月04日 03:59"
      },
      {
        "type": "text",
        "text": "[卫戍协议数据包]"
      },
      {
        "type": "text",
        "text": "组合包内容： 模组数据块*12"
      },
      {
        "type": "text",
        "text": "[卫戍协议数据套组]"
      },
      {
        "type": "text",
        "text": "组合包内容： 模组数据块*24、数据增补仪*30、数据增补条*90"
      },
      {
        "type": "text",
        "text": "更多活动内容请持续关注《明日方舟》游戏内公告及官方公告。"
      },
      {
        "type": "text",
        "text": "【明日方舟】运营组"
      },
      {
        "type": "text",
        "text": "2026年03月11日"
      }
    ]
  },
  {
    "cid": "6252",
    "title": "[活动预告]故事集「十字路口」限时活动即将开启",
    "tab": "1",
    "month": "2026-03",
    "date": "2026 // 03 / 05",
    "ts": 1772679600.0,
    "source_url": "https://ak.hypergryph.com/news/6252",
    "blocks": [
      {
        "type": "image",
        "src": "https://raw.githubusercontent.com/Jackie751/report/main/test/%E6%B4%BB%E5%8A%A8/2026___03___05_6252_%5B%E6%B4%BB%E5%8A%A8%E9%A2%84%E5%91%8A%5D%E6%95%85%E4%BA%8B%E9%9B%86%E3%80%8C%E5%8D%81%E5%AD%97%E8%B7%AF%E5%8F%A3%E3%80%8D%E9%99%90%E6%97%B6%E6%B4%BB%E5%8A%A8%E5%8D%B3%E5%B0%86%E5%BC%80%E5%90%AF/01_8549ee1ada048f23ae88b87a5148bba1_8db6cba4.jpg",
        "original_src": "https://web.hycdn.cn/upload/image/20260302/8549ee1ada048f23ae88b87a5148bba1.jpg"
      },
      {
        "type": "text",
        "text": "一、故事集「十字路口」限时开启"
      },
      {
        "type": "text",
        "text": "关卡开放时间： 03月10日 12:00 - 03月17日 03:59"
      },
      {
        "type": "text",
        "text": "关卡解锁条件： 通关主线1-10"
      },
      {
        "type": "text",
        "text": "关卡掉落： 软木瓶塞、素材等"
      },
      {
        "type": "text",
        "text": "活动说明： 活动期间将限时开放「十字路口」活动关卡，玩家可通过活动作战收集「软木瓶塞」后在【红酒锦标赛筹委会】中兑换活动奖励及事相碎片，事相碎片可用于当期及往期故事集的剧情解锁"
      },
      {
        "type": "text",
        "text": "◆本次活动开启时间存在提前或延迟的可能，详情请关注后续公告"
      },
      {
        "type": "image",
        "src": "https://raw.githubusercontent.com/Jackie751/report/main/test/%E6%B4%BB%E5%8A%A8/2026___03___05_6252_%5B%E6%B4%BB%E5%8A%A8%E9%A2%84%E5%91%8A%5D%E6%95%85%E4%BA%8B%E9%9B%86%E3%80%8C%E5%8D%81%E5%AD%97%E8%B7%AF%E5%8F%A3%E3%80%8D%E9%99%90%E6%97%B6%E6%B4%BB%E5%8A%A8%E5%8D%B3%E5%B0%86%E5%BC%80%E5%90%AF/02_e59a9a5ef3af002b1739818f016faecd_5d40af70.jpg",
        "original_src": "https://web.hycdn.cn/upload/image/20260302/e59a9a5ef3af002b1739818f016faecd.jpg"
      },
      {
        "type": "text",
        "text": "【红酒锦标赛筹委会】兑换时间： 03月10日 12:00 - 03月20日 03:59"
      },
      {
        "type": "text",
        "text": "【红酒锦标赛筹委会】兑换奖励： 时装【时代系列 - 三元风情 - 红隼】、事相碎片、 模组养成材料、高级养成素材、作战记录、龙门币、招聘许可等"
      },
      {
        "type": "text",
        "text": "注意："
      },
      {
        "type": "text",
        "text": "◆本次活动结束后该故事集将收录至【情报处理室】中"
      },
      {
        "type": "image",
        "src": "https://raw.githubusercontent.com/Jackie751/report/main/test/%E6%B4%BB%E5%8A%A8/2026___03___05_6252_%5B%E6%B4%BB%E5%8A%A8%E9%A2%84%E5%91%8A%5D%E6%95%85%E4%BA%8B%E9%9B%86%E3%80%8C%E5%8D%81%E5%AD%97%E8%B7%AF%E5%8F%A3%E3%80%8D%E9%99%90%E6%97%B6%E6%B4%BB%E5%8A%A8%E5%8D%B3%E5%B0%86%E5%BC%80%E5%90%AF/03_5b219c575e84d59381a1919019d40274_4dd9dd83.jpg",
        "original_src": "https://web.hycdn.cn/upload/image/20260302/5b219c575e84d59381a1919019d40274.jpg"
      },
      {
        "type": "text",
        "text": "二、【以我的方式】限时寻访开启"
      },
      {
        "type": "text",
        "text": "活动时间： 03月10日 12:00 - 03月24日 03:59"
      },
      {
        "type": "text",
        "text": "活动说明： 活动期间【以我的方式】限时寻访开启，该寻访中以下干员出现率上升"
      },
      {
        "type": "text",
        "text": "★★★★★★：贝洛内（占6★出率的50%）"
      },
      {
        "type": "text",
        "text": "★★★★★： 复奏 / 洋灰（占5★出率的50%）"
      },
      {
        "type": "text",
        "text": "◆本次活动【以我的方式】寻访为【标准寻访】，如果连续150次没有获得该限时寻访中出率上升的六星干员，则下一次招募到的六星干员必定为该限时寻访中出率上升的六星干员"
      },
      {
        "type": "image",
        "src": "https://raw.githubusercontent.com/Jackie751/report/main/test/%E6%B4%BB%E5%8A%A8/2026___03___05_6252_%5B%E6%B4%BB%E5%8A%A8%E9%A2%84%E5%91%8A%5D%E6%95%85%E4%BA%8B%E9%9B%86%E3%80%8C%E5%8D%81%E5%AD%97%E8%B7%AF%E5%8F%A3%E3%80%8D%E9%99%90%E6%97%B6%E6%B4%BB%E5%8A%A8%E5%8D%B3%E5%B0%86%E5%BC%80%E5%90%AF/04_0cab2995e8025c9a88b297d5d4adef61_cfe15db0.jpg",
        "original_src": "https://web.hycdn.cn/upload/image/20260302/0cab2995e8025c9a88b297d5d4adef61.jpg"
      },
      {
        "type": "text",
        "text": "三、新干员登场，信赖获取提升"
      },
      {
        "type": "text",
        "text": "新增干员： 以下新增干员除加入【以我的方式】寻访外，将在03月12日04:00后加入并常驻其余【标准寻访】卡池"
      },
      {
        "type": "text",
        "text": "★★★★★★：贝洛内"
      },
      {
        "type": "text",
        "text": "★★★★★： 复奏"
      },
      {
        "type": "text",
        "text": "◆本次活动关卡开放期间以上新增干员信赖获取提升"
      },
      {
        "type": "image",
        "src": "https://raw.githubusercontent.com/Jackie751/report/main/test/%E6%B4%BB%E5%8A%A8/2026___03___05_6252_%5B%E6%B4%BB%E5%8A%A8%E9%A2%84%E5%91%8A%5D%E6%95%85%E4%BA%8B%E9%9B%86%E3%80%8C%E5%8D%81%E5%AD%97%E8%B7%AF%E5%8F%A3%E3%80%8D%E9%99%90%E6%97%B6%E6%B4%BB%E5%8A%A8%E5%8D%B3%E5%B0%86%E5%BC%80%E5%90%AF/05_047ec3f249a0bb93af94d0a5036f6bf3_1dae6b6b.jpg",
        "original_src": "https://web.hycdn.cn/upload/image/20260302/047ec3f249a0bb93af94d0a5036f6bf3.jpg"
      },
      {
        "type": "text",
        "text": "四、常驻回归系统优化"
      },
      {
        "type": "text",
        "text": "更新时间： 03月10日 12:00"
      },
      {
        "type": "text",
        "text": "更新说明： 03月10日 12:00版本更新后，触发常驻回归系统所需的离线时长将由60天下调至30天（常驻回归系统部分内容将根据离线时长有所区别，详情请以游戏内为准），回归任务类型也进行了优化；此外，满足指定条件的玩家还可参与【归航寻访】、触发【剿灭作战】关卡限时全开效果"
      },
      {
        "type": "text",
        "text": "◆更新后的常驻回归系统将移除每日补给，尚未领取的每日补给应急理智加强剂将通过邮件一次性发放；在更新前已触发回归系统的玩家，更新后任务内容及完成进度将保持不变"
      },
      {
        "type": "text",
        "text": "◆距离上次离线时长≥180天的玩家可参与【归航寻访】，玩家可在指定范围内自主选择并锁定3名6星干员和3名5星干员作为概率提升的干员（【归航寻访】可能出现的6星干员仅包括自选概率提升的3名6星干员，详细寻访说明请参照游戏内介绍），首期【归航寻访】包含的6星干员： 焰影苇草、仇白、提丰、圣约送葬人、莱伊、阿斯卡纶 ，后续【归航寻访】干员范围调整请参照相关公告说明"
      },
      {
        "type": "text",
        "text": "◆在任意两个不同的【归航寻访】中，没有获得6星干员的累计次数不会累计，该次数会因为【归航寻访】的结束而清零。因为累计次数而增加的获得概率，不会应用于接下来任意一次【归航寻访】；【归航寻访】中，没有获得6星干员的抽取次数不会累计/应用到其他任意寻访，与其他任意寻访的已有累计次数互不影响"
      },
      {
        "type": "text",
        "text": "◆自03月26日04:00起，所有【标准寻访】及【限定寻访】将不再包含以下干员："
      },
      {
        "type": "text",
        "text": "★★★★★★：老鲤/澄闪/菲亚梅塔/号角/艾丽妮/黑键/多萝西"
      },
      {
        "type": "text",
        "text": "★★★★★：夜半/夏栎/风丸/洛洛/掠风/濯尘芙蓉/承曦格雷伊"
      },
      {
        "type": "text",
        "text": "以上干员将从04月16日04:00起进入【中坚寻访】；此外，【归航寻访】将不会包含上述干员"
      },
      {
        "type": "image",
        "src": "https://raw.githubusercontent.com/Jackie751/report/main/test/%E6%B4%BB%E5%8A%A8/2026___03___05_6252_%5B%E6%B4%BB%E5%8A%A8%E9%A2%84%E5%91%8A%5D%E6%95%85%E4%BA%8B%E9%9B%86%E3%80%8C%E5%8D%81%E5%AD%97%E8%B7%AF%E5%8F%A3%E3%80%8D%E9%99%90%E6%97%B6%E6%B4%BB%E5%8A%A8%E5%8D%B3%E5%B0%86%E5%BC%80%E5%90%AF/06_85fec858f7831dff179a1b87043e6410_eeab7ba7.jpg",
        "original_src": "https://web.hycdn.cn/upload/image/20260302/85fec858f7831dff179a1b87043e6410.jpg"
      },
      {
        "type": "text",
        "text": "五、归航同步礼盒上架"
      },
      {
        "type": "text",
        "text": "活动说明： 采购中心将售卖以下组合包"
      },
      {
        "type": "text",
        "text": "[归航同步礼盒]"
      },
      {
        "type": "text",
        "text": "上架时间： 03月10日 12:00"
      },
      {
        "type": "text",
        "text": "可购买时间： 03月10日 12:00后触发常驻回归系统的触发日起14天内"
      },
      {
        "type": "text",
        "text": "可购买人群： 03月10日 12:00后触发常驻回归系统，且距离上次离线时长≥60天的玩家"
      },
      {
        "type": "text",
        "text": "组合包内容： 03月10日 12:00后触发常驻回归系统的触发日起21天内，购买礼包的玩家可基于已累计登录天数立即获得对应天数的至纯源石、合成玉、自助芯片印刻仪等物品（购买前累计登录天数也计入）"
      },
      {
        "type": "text",
        "text": "累计登录第1天获得：至纯源石*1、 自助芯片印刻仪*1"
      },
      {
        "type": "text",
        "text": "累计登录第2天获得：中级作战记录*10"
      },
      {
        "type": "text",
        "text": "累计登录第3天获得：合成玉*600"
      },
      {
        "type": "text",
        "text": "累计登录第4天获得：高级材料提货券*5"
      },
      {
        "type": "text",
        "text": "累计登录第5天获得：合成玉*200"
      },
      {
        "type": "text",
        "text": "累计登录第6天获得：技巧概要·卷3*8"
      },
      {
        "type": "text",
        "text": "累计登录第7天获得：龙门币*60000"
      },
      {
        "type": "text",
        "text": "自助芯片印刻仪： 使用后可自选任一职业芯片5个"
      },
      {
        "type": "text",
        "text": "◆03月10日 06:00前触发常驻回归系统的玩家在指定时间内可购买原有的[归航适应礼盒]，无法购买[归航同步礼盒]"
      },
      {
        "type": "image",
        "src": "https://raw.githubusercontent.com/Jackie751/report/main/test/%E6%B4%BB%E5%8A%A8/2026___03___05_6252_%5B%E6%B4%BB%E5%8A%A8%E9%A2%84%E5%91%8A%5D%E6%95%85%E4%BA%8B%E9%9B%86%E3%80%8C%E5%8D%81%E5%AD%97%E8%B7%AF%E5%8F%A3%E3%80%8D%E9%99%90%E6%97%B6%E6%B4%BB%E5%8A%A8%E5%8D%B3%E5%B0%86%E5%BC%80%E5%90%AF/07_edc0cc6a5cf1fbd9cb41a10a553dffe6_aed19910.jpg",
        "original_src": "https://web.hycdn.cn/upload/image/20260302/edc0cc6a5cf1fbd9cb41a10a553dffe6.jpg"
      },
      {
        "type": "text",
        "text": "六、【成就之星】系列，新装限时上架"
      },
      {
        "type": "text",
        "text": "活动说明： 活动期间以下干员新增时装将在时装商店上架并进行限时贩售："
      },
      {
        "type": "text",
        "text": "◆【成就之星】系列 - 血翼蔷薇 - 司霆惊蛰"
      },
      {
        "type": "text",
        "text": "◆【成就之星】系列 - 乱数法则 - 电弧"
      },
      {
        "type": "text",
        "text": "◆【成就之星】系列 - 下一个任务 - 莎草"
      },
      {
        "type": "image",
        "src": "https://raw.githubusercontent.com/Jackie751/report/main/test/%E6%B4%BB%E5%8A%A8/2026___03___05_6252_%5B%E6%B4%BB%E5%8A%A8%E9%A2%84%E5%91%8A%5D%E6%95%85%E4%BA%8B%E9%9B%86%E3%80%8C%E5%8D%81%E5%AD%97%E8%B7%AF%E5%8F%A3%E3%80%8D%E9%99%90%E6%97%B6%E6%B4%BB%E5%8A%A8%E5%8D%B3%E5%B0%86%E5%BC%80%E5%90%AF/08_5af8681551dc266d1bea58908f2f098e_f4817395.jpg",
        "original_src": "https://web.hycdn.cn/upload/image/20260302/5af8681551dc266d1bea58908f2f098e.jpg"
      },
      {
        "type": "text",
        "text": "七、复刻时装限时上架"
      },
      {
        "type": "text",
        "text": "活动说明： 活动期间以下干员时装将在时装商店上架并进行限时贩售："
      },
      {
        "type": "text",
        "text": "◆【时代】系列 - 甜美配方 - 妮芙"
      },
      {
        "type": "text",
        "text": "◆【时代】系列 - 林间暖阳 - 凛视"
      },
      {
        "type": "text",
        "text": "◆【时代】系列 - 绒布蛋糕 - 坚雷"
      },
      {
        "type": "text",
        "text": "◆【成就之星】系列 - 万物有灵 - 慑砂"
      },
      {
        "type": "image",
        "src": "https://raw.githubusercontent.com/Jackie751/report/main/test/%E6%B4%BB%E5%8A%A8/2026___03___05_6252_%5B%E6%B4%BB%E5%8A%A8%E9%A2%84%E5%91%8A%5D%E6%95%85%E4%BA%8B%E9%9B%86%E3%80%8C%E5%8D%81%E5%AD%97%E8%B7%AF%E5%8F%A3%E3%80%8D%E9%99%90%E6%97%B6%E6%B4%BB%E5%8A%A8%E5%8D%B3%E5%B0%86%E5%BC%80%E5%90%AF/09_184741245b8b15024ab28e2d4b575dbf_1540612a.jpg",
        "original_src": "https://web.hycdn.cn/upload/image/20260302/184741245b8b15024ab28e2d4b575dbf.jpg"
      },
      {
        "type": "text",
        "text": "八、新增【威尔德披萨餐厅】主题家具，限时上架"
      },
      {
        "type": "text",
        "text": "家具商店贩售时间 ：03月10日 12:00 - 03月24日 03:59"
      },
      {
        "type": "image",
        "src": "https://raw.githubusercontent.com/Jackie751/report/main/test/%E6%B4%BB%E5%8A%A8/2026___03___05_6252_%5B%E6%B4%BB%E5%8A%A8%E9%A2%84%E5%91%8A%5D%E6%95%85%E4%BA%8B%E9%9B%86%E3%80%8C%E5%8D%81%E5%AD%97%E8%B7%AF%E5%8F%A3%E3%80%8D%E9%99%90%E6%97%B6%E6%B4%BB%E5%8A%A8%E5%8D%B3%E5%B0%86%E5%BC%80%E5%90%AF/10_47da7f0b18eec841e5fdd41c8cd84241_3c4d7c5b.jpg",
        "original_src": "https://web.hycdn.cn/upload/image/20260302/47da7f0b18eec841e5fdd41c8cd84241.jpg"
      },
      {
        "type": "text",
        "text": "九、组合包限时上架"
      },
      {
        "type": "text",
        "text": "活动时间： 03月10日 12:00 - 03月31日 03:59"
      },
      {
        "type": "text",
        "text": "活动说明： 活动期间，采购中心将限时售卖以下组合包"
      },
      {
        "type": "text",
        "text": "[界园志异特训组合]"
      },
      {
        "type": "text",
        "text": "组合包内容： 高级资深干员特训邀请函*1、资深干员特训邀请函*1、专业干员特训邀请函*2"
      },
      {
        "type": "text",
        "text": "高级资深干员特训邀请函： 使用该邀请函后可选择一名任意等级，但未晋升至精英阶段2的6星干员直接晋升至精英阶段2，等级1。干员晋升后不会返还已投入的养成资源"
      },
      {
        "type": "text",
        "text": "[近卫芯片礼包]"
      },
      {
        "type": "text",
        "text": "组合包内容： 近卫双芯片*4、近卫芯片*5、技巧概要·卷3*45、技巧概要·卷2*25、技巧概要·卷1*10"
      },
      {
        "type": "text",
        "text": "[酿造装置资金箱]"
      },
      {
        "type": "text",
        "text": "组合包内容： 至纯源石*13、龙门币*300000"
      },
      {
        "type": "image",
        "src": "https://raw.githubusercontent.com/Jackie751/report/main/test/%E6%B4%BB%E5%8A%A8/2026___03___05_6252_%5B%E6%B4%BB%E5%8A%A8%E9%A2%84%E5%91%8A%5D%E6%95%85%E4%BA%8B%E9%9B%86%E3%80%8C%E5%8D%81%E5%AD%97%E8%B7%AF%E5%8F%A3%E3%80%8D%E9%99%90%E6%97%B6%E6%B4%BB%E5%8A%A8%E5%8D%B3%E5%B0%86%E5%BC%80%E5%90%AF/11_f84b38ee22e90cac19062063b9690918_ddea895f.jpg",
        "original_src": "https://web.hycdn.cn/upload/image/20260302/f84b38ee22e90cac19062063b9690918.jpg"
      },
      {
        "type": "text",
        "text": "十、采购中心【高级凭证区】&【通用凭证区】可兑换内容追加"
      },
      {
        "type": "text",
        "text": "活动内容： 采购中心凭证交易所【高级凭证区】&【通用凭证区】将新增上架以下内容可供兑换："
      },
      {
        "type": "text",
        "text": "◆【时代】系列 - 光影 - 夜魔"
      },
      {
        "type": "text",
        "text": "◆【0011制造】系列 - 孤寒峭 - 絮雨"
      },
      {
        "type": "text",
        "text": "更多活动内容请持续关注《明日方舟》游戏内公告及官方公告。"
      },
      {
        "type": "text",
        "text": "【明日方舟】运营组"
      },
      {
        "type": "text",
        "text": "2026年03月05日"
      }
    ]
  },
  {
    "cid": "9698",
    "title": "《明日方舟》制作组通讯#62期",
    "tab": "2",
    "month": "2026-02",
    "date": "2026 // 02 / 24",
    "ts": 1771923600.0,
    "source_url": "https://ak.hypergryph.com/news/9698",
    "blocks": [
      {
        "type": "text",
        "text": "感谢大家一直以来对《明日方舟》的关注与支持，很高兴和大家再次见面。在本期制作组通讯发布之际，矢量突破#2「巫术之夜」限时活动已经开启，欢迎大家进行体验，同时也再次感谢大家对于此前SideStory「辞岁行」的喜爱与支持。"
      },
      {
        "type": "text",
        "text": "以下，则是本次制作组通讯为大家带来的最新一期的相关活动及版本内容："
      },
      {
        "type": "image",
        "src": "https://raw.githubusercontent.com/Jackie751/report/main/test/%E5%88%B6%E4%BD%9C%E7%BB%84%E9%80%9A%E8%AE%AF/2026___02___24_9698_%E3%80%8A%E6%98%8E%E6%97%A5%E6%96%B9%E8%88%9F%E3%80%8B%E5%88%B6%E4%BD%9C%E7%BB%84%E9%80%9A%E8%AE%AF%2362%E6%9C%9F/01_7cdf2173f6d083c9f05d94521bcbe5cb_27a62587.png",
        "original_src": "https://web.hycdn.cn/upload/image/20260224/7cdf2173f6d083c9f05d94521bcbe5cb.png"
      },
      {
        "type": "text",
        "text": "【通讯节点·一】"
      },
      {
        "type": "text",
        "text": "●“你制定的规则与我践行的方式将成为这座城市全新的‘铳与秩序’，莱昂图索。”"
      },
      {
        "type": "text",
        "text": "●故事集「十字路口」限时活动将于3月上旬开启，该活动除包含全新活动关卡与剧情外，新干员、新时装以及相关主题家具也将伴随本次活动登场及上架。"
      },
      {
        "type": "image",
        "src": "https://raw.githubusercontent.com/Jackie751/report/main/test/%E5%88%B6%E4%BD%9C%E7%BB%84%E9%80%9A%E8%AE%AF/2026___02___24_9698_%E3%80%8A%E6%98%8E%E6%97%A5%E6%96%B9%E8%88%9F%E3%80%8B%E5%88%B6%E4%BD%9C%E7%BB%84%E9%80%9A%E8%AE%AF%2362%E6%9C%9F/02_9f40090d3d867e8608b568e4f4df9ae8_4b588347.jpg",
        "original_src": "https://web.hycdn.cn/upload/image/20260224/9f40090d3d867e8608b568e4f4df9ae8.jpg"
      },
      {
        "type": "text",
        "text": "【通讯节点·二】"
      },
      {
        "type": "text",
        "text": "●集成战略主题【岁的界园志异】内容拓展三将于3月上旬开启，本次内容拓展将开启【深入探索】模式，更多内容请关注后续官方自媒体相关介绍。"
      },
      {
        "type": "image",
        "src": "https://raw.githubusercontent.com/Jackie751/report/main/test/%E5%88%B6%E4%BD%9C%E7%BB%84%E9%80%9A%E8%AE%AF/2026___02___24_9698_%E3%80%8A%E6%98%8E%E6%97%A5%E6%96%B9%E8%88%9F%E3%80%8B%E5%88%B6%E4%BD%9C%E7%BB%84%E9%80%9A%E8%AE%AF%2362%E6%9C%9F/03_7988f93f231d9cccd3a9abe56d324cdd_dae19745.jpg",
        "original_src": "https://web.hycdn.cn/upload/image/20260224/7988f93f231d9cccd3a9abe56d324cdd.jpg"
      },
      {
        "type": "text",
        "text": "【通讯节点·三】"
      },
      {
        "type": "text",
        "text": "●「卫戍协议：盟约」下半期活动将于3月中旬开启，本期活动优化了独立模拟与联合模拟的体验，还将包含新难度、新盟约、新策略等多种新内容，更多内容请关注后续官方自媒体相关介绍。"
      },
      {
        "type": "image",
        "src": "https://raw.githubusercontent.com/Jackie751/report/main/test/%E5%88%B6%E4%BD%9C%E7%BB%84%E9%80%9A%E8%AE%AF/2026___02___24_9698_%E3%80%8A%E6%98%8E%E6%97%A5%E6%96%B9%E8%88%9F%E3%80%8B%E5%88%B6%E4%BD%9C%E7%BB%84%E9%80%9A%E8%AE%AF%2362%E6%9C%9F/04_8e1023e528097fec2da70d3884428dbb_37063f4c.jpg",
        "original_src": "https://web.hycdn.cn/upload/image/20260224/8e1023e528097fec2da70d3884428dbb.jpg"
      },
      {
        "type": "text",
        "text": "【通讯节点·四】"
      },
      {
        "type": "text",
        "text": "●SideStory「挽歌燃烧殆尽」复刻活动将于3月下旬开启，【自火中归还】限时寻访将同期进行复刻，该活动同期上架的家具也将限时复刻。此外，还将有【时代】系列全新时装在本次复刻活动中上架贩售。"
      },
      {
        "type": "text",
        "text": "注意："
      },
      {
        "type": "text",
        "text": "本次复刻活动关卡将继承玩家此前的活动关卡进度及首次掉落进度；"
      },
      {
        "type": "text",
        "text": "本次复刻活动结束后该活动关卡将常驻至【曲谱】；"
      },
      {
        "type": "text",
        "text": "本次复刻活动中部分无法重复获得的活动奖励将在重复获得时按照对应比例兑换为【情报凭证】，【情报凭证】兑换比例可参照活动中相应【情报凭证转换规则】；"
      },
      {
        "type": "text",
        "text": "【情报凭证】商店内物品将在活动开启时在原有的商品数量上进行叠加补货及新增其他商品。"
      },
      {
        "type": "text",
        "text": "奖励内容： 合成玉*200、半自然溶剂*5"
      },
      {
        "type": "text",
        "text": "发放时间： 02月24日17:00（邮件领取有效期：7日）"
      },
      {
        "type": "text",
        "text": "发放范围： 02月24日17:00前所有注册并创建角色的玩家"
      },
      {
        "type": "text",
        "text": "*制作组通讯并不代表版本更新及活动最终内容，详细活动计划与版本更新内容等请以届时相关公告为准*"
      },
      {
        "type": "text",
        "text": "《明日方舟》制作组"
      },
      {
        "type": "text",
        "text": "2026年02月24日"
      }
    ]
  },
  {
    "cid": "7375",
    "title": "[活动预告]矢量突破#2「巫术之夜」限时活动即将开启",
    "tab": "1",
    "month": "2026-02",
    "date": "2026 // 02 / 19",
    "ts": 1771470000.0,
    "source_url": "https://ak.hypergryph.com/news/7375",
    "blocks": [
      {
        "type": "image",
        "src": "https://raw.githubusercontent.com/Jackie751/report/main/test/%E6%B4%BB%E5%8A%A8/2026___02___19_7375_%5B%E6%B4%BB%E5%8A%A8%E9%A2%84%E5%91%8A%5D%E7%9F%A2%E9%87%8F%E7%AA%81%E7%A0%B4%232%E3%80%8C%E5%B7%AB%E6%9C%AF%E4%B9%8B%E5%A4%9C%E3%80%8D%E9%99%90%E6%97%B6%E6%B4%BB%E5%8A%A8%E5%8D%B3%E5%B0%86%E5%BC%80%E5%90%AF/01_5f5aabc0ca65ada1dbdd0140c33c7a7c_ccf862ed.jpg",
        "original_src": "https://web.hycdn.cn/upload/image/20260213/5f5aabc0ca65ada1dbdd0140c33c7a7c.jpg"
      },
      {
        "type": "text",
        "text": "一、矢量突破#2「巫术之夜」限时活动开启"
      },
      {
        "type": "text",
        "text": "关卡开放时间： 02月24日 16:00 - 03月17日 03:59"
      },
      {
        "type": "text",
        "text": "解锁条件： 通关主线 2-10"
      },
      {
        "type": "text",
        "text": "活动说明： 活动期间将开放「矢量突破」限时活动，玩家可通过活动关卡作战获取【“小心地滑”】，提升【突破里程碑】等级获取相应活动奖励"
      },
      {
        "type": "text",
        "text": "【突破里程碑】开放时间： 02月24日 16:00 - 03月20日 03:59"
      },
      {
        "type": "text",
        "text": "【突破里程碑】主要奖励： 时装 【时代系列 - 都会送报员 - 格雷伊】 、活动家具、模组养成材料、高级养成素材、作战记录、龙门币等"
      },
      {
        "type": "image",
        "src": "https://raw.githubusercontent.com/Jackie751/report/main/test/%E6%B4%BB%E5%8A%A8/2026___02___19_7375_%5B%E6%B4%BB%E5%8A%A8%E9%A2%84%E5%91%8A%5D%E7%9F%A2%E9%87%8F%E7%AA%81%E7%A0%B4%232%E3%80%8C%E5%B7%AB%E6%9C%AF%E4%B9%8B%E5%A4%9C%E3%80%8D%E9%99%90%E6%97%B6%E6%B4%BB%E5%8A%A8%E5%8D%B3%E5%B0%86%E5%BC%80%E5%90%AF/02_0e291dad3c836d69dcf2c92694e6d5e6_b00b459f.jpg",
        "original_src": "https://web.hycdn.cn/upload/image/20260213/0e291dad3c836d69dcf2c92694e6d5e6.jpg"
      },
      {
        "type": "text",
        "text": "二、“资源收集”关卡限时全天开放"
      },
      {
        "type": "text",
        "text": "活动时间： 02月24日 16:00 - 03月17日 03:59"
      },
      {
        "type": "text",
        "text": "活动说明： 活动期间内“资源收集”所有关卡将进行全天开放"
      },
      {
        "type": "image",
        "src": "https://raw.githubusercontent.com/Jackie751/report/main/test/%E6%B4%BB%E5%8A%A8/2026___02___19_7375_%5B%E6%B4%BB%E5%8A%A8%E9%A2%84%E5%91%8A%5D%E7%9F%A2%E9%87%8F%E7%AA%81%E7%A0%B4%232%E3%80%8C%E5%B7%AB%E6%9C%AF%E4%B9%8B%E5%A4%9C%E3%80%8D%E9%99%90%E6%97%B6%E6%B4%BB%E5%8A%A8%E5%8D%B3%E5%B0%86%E5%BC%80%E5%90%AF/03_94ca76520e48c4b2cca5b2c02169e913_5f2a9dbf.jpg",
        "original_src": "https://web.hycdn.cn/upload/image/20260213/94ca76520e48c4b2cca5b2c02169e913.jpg"
      },
      {
        "type": "text",
        "text": "三、【定向甄选】限时寻访开启"
      },
      {
        "type": "text",
        "text": "活动时间： 02月24日 16:00 - 03月10日 03:59"
      },
      {
        "type": "text",
        "text": "活动说明： 活动期间，玩家可在 当期甄选的干员范围内自主选择并锁定3名六星干员和3名五星干员 作为当期【定向甄选】寻访出现概率提升的干员（当期【定向甄选】可能出现的六星干员仅包括自选概率提升的3名六星干员）"
      },
      {
        "type": "text",
        "text": "当期可选择概率提升的干员范围："
      },
      {
        "type": "text",
        "text": "★★★★★★（6★出率：2%）：遥 / Mon3tr / 逻各斯 / 阿斯卡纶 / 维娜·维多利亚 / 艾丽妮"
      },
      {
        "type": "text",
        "text": "★★★★★（5★出率：8%）：夜半 / 折桠 / 承曦格雷伊 / 刺玫 / 录武官 / 晓歌"
      },
      {
        "type": "text",
        "text": "注意："
      },
      {
        "type": "text",
        "text": "◆本次活动【定向甄选】寻访为【标准寻访】，在选定概率提升的干员后， 当期【定向甄选】可能出现的六星干员仅包括自选概率提升的3名六星干员，其合计出现概率占六星干员出率的100%；该卡池可能出现的五星干员包括标准寻访中全部五星干员，自选UP的3名五星干员出现概率提升 ，其合计出现概率占五星干员出率的60%"
      },
      {
        "type": "image",
        "src": "https://raw.githubusercontent.com/Jackie751/report/main/test/%E6%B4%BB%E5%8A%A8/2026___02___19_7375_%5B%E6%B4%BB%E5%8A%A8%E9%A2%84%E5%91%8A%5D%E7%9F%A2%E9%87%8F%E7%AA%81%E7%A0%B4%232%E3%80%8C%E5%B7%AB%E6%9C%AF%E4%B9%8B%E5%A4%9C%E3%80%8D%E9%99%90%E6%97%B6%E6%B4%BB%E5%8A%A8%E5%8D%B3%E5%B0%86%E5%BC%80%E5%90%AF/04_5427257823028ca816ad28822a7a7064_9a2a2a15.jpg",
        "original_src": "https://web.hycdn.cn/upload/image/20260213/5427257823028ca816ad28822a7a7064.jpg"
      },
      {
        "type": "text",
        "text": "四、组合包限时上架"
      },
      {
        "type": "text",
        "text": "活动说明： 活动期间，采购中心将限时售卖以下组合包"
      },
      {
        "type": "text",
        "text": "[定向甄选寻访组合包]"
      },
      {
        "type": "text",
        "text": "组合包内容： 十连寻访凭证*2、至纯源石*9"
      },
      {
        "type": "text",
        "text": "[罗德岛数据套组]"
      },
      {
        "type": "text",
        "text": "组合包内容： 模组数据块*24、数据增补仪*30、数据增补条*90"
      },
      {
        "type": "text",
        "text": "[罗德岛数据包]"
      },
      {
        "type": "text",
        "text": "组合包内容： 模组数据块*12"
      },
      {
        "type": "image",
        "src": "https://raw.githubusercontent.com/Jackie751/report/main/test/%E6%B4%BB%E5%8A%A8/2026___02___19_7375_%5B%E6%B4%BB%E5%8A%A8%E9%A2%84%E5%91%8A%5D%E7%9F%A2%E9%87%8F%E7%AA%81%E7%A0%B4%232%E3%80%8C%E5%B7%AB%E6%9C%AF%E4%B9%8B%E5%A4%9C%E3%80%8D%E9%99%90%E6%97%B6%E6%B4%BB%E5%8A%A8%E5%8D%B3%E5%B0%86%E5%BC%80%E5%90%AF/05_a3003fb179aaa821d910db86d85e119a_21e0b229.jpg",
        "original_src": "https://web.hycdn.cn/upload/image/20260213/a3003fb179aaa821d910db86d85e119a.jpg"
      },
      {
        "type": "text",
        "text": "五、【时代】系列，限时复刻上架"
      },
      {
        "type": "text",
        "text": "活动说明： 活动期间以下干员时装将在时装商店上架并限时贩售："
      },
      {
        "type": "text",
        "text": "◆【时代】系列 - 寄自奥格尼斯科 - 薇薇安娜"
      },
      {
        "type": "text",
        "text": "◆【时代】系列 - 风笛声声 - 风笛"
      },
      {
        "type": "text",
        "text": "◆【时代】系列 - 繁霜满阶 - 缠丸"
      },
      {
        "type": "text",
        "text": "更多活动内容请持续关注《明日方舟》游戏内公告及官方公告。"
      },
      {
        "type": "text",
        "text": "【明日方舟】运营组"
      },
      {
        "type": "text",
        "text": "2026年02月19日"
      }
    ]
  },
  {
    "cid": "4942",
    "title": "[活动预告]辞旧迎新，SideStory「辞岁行」即将开启",
    "tab": "1",
    "month": "2026-02",
    "date": "2026 // 02 / 06",
    "ts": 1770381000.0,
    "source_url": "https://ak.hypergryph.com/news/4942",
    "blocks": [
      {
        "type": "image",
        "src": "https://raw.githubusercontent.com/Jackie751/report/main/test/%E6%B4%BB%E5%8A%A8/2026___02___06_4942_%5B%E6%B4%BB%E5%8A%A8%E9%A2%84%E5%91%8A%5D%E8%BE%9E%E6%97%A7%E8%BF%8E%E6%96%B0%EF%BC%8CSideStory%E3%80%8C%E8%BE%9E%E5%B2%81%E8%A1%8C%E3%80%8D%E5%8D%B3%E5%B0%86%E5%BC%80%E5%90%AF/01_90d6bf4cfe7aee3665d2af791c27f2ab_f3e86a2b.jpg",
        "original_src": "https://web.hycdn.cn/upload/image/20260205/90d6bf4cfe7aee3665d2af791c27f2ab.jpg"
      },
      {
        "type": "text",
        "text": "一、全新SideStory「辞岁行」，活动关卡开启"
      },
      {
        "type": "text",
        "text": "活动时间： 02月10日 12:00 - 03月10日 03:59"
      },
      {
        "type": "text",
        "text": "解锁条件： 通关主线1-10"
      },
      {
        "type": "text",
        "text": "活动说明： 活动期间将开放「辞岁行」活动关卡，玩家可通过活动关卡作战、完成相关活动任务以及活动商店获取相关活动奖励"
      },
      {
        "type": "text",
        "text": "活动关卡将进行分段式开启："
      },
      {
        "type": "text",
        "text": "◆「霜秋实录」开启时间 ：02月10日 12:00 - 03月03日 03:59"
      },
      {
        "type": "text",
        "text": "◆「望春遗事」开启时间 ：02月17日 16:00 - 03月03日 03:59"
      },
      {
        "type": "text",
        "text": "◆「待笔新篇」开启时间 ：02月24日 16:00 - 03月03日 03:59"
      },
      {
        "type": "text",
        "text": "◆本次活动开启时间存在提前或延迟的可能，详情请关注后续公告"
      },
      {
        "type": "image",
        "src": "https://raw.githubusercontent.com/Jackie751/report/main/test/%E6%B4%BB%E5%8A%A8/2026___02___06_4942_%5B%E6%B4%BB%E5%8A%A8%E9%A2%84%E5%91%8A%5D%E8%BE%9E%E6%97%A7%E8%BF%8E%E6%96%B0%EF%BC%8CSideStory%E3%80%8C%E8%BE%9E%E5%B2%81%E8%A1%8C%E3%80%8D%E5%8D%B3%E5%B0%86%E5%BC%80%E5%90%AF/02_c59b0ab939f7b4d2f1ff79a3bc130429_6881af92.jpg",
        "original_src": "https://web.hycdn.cn/upload/image/20260205/c59b0ab939f7b4d2f1ff79a3bc130429.jpg"
      },
      {
        "type": "text",
        "text": "【岁时考异】"
      },
      {
        "type": "text",
        "text": "活动说明： 活动期间，玩家可通过活动关卡作战完成【岁时考异】中相关任务获取奖励"
      },
      {
        "type": "text",
        "text": "主要奖励： 活动干员 【★★★★★：矩】 、 【天镜阁会客堂】家具（部分） 、模组养成材料、「未定稿」等"
      },
      {
        "type": "text",
        "text": "【天镜茶室】"
      },
      {
        "type": "text",
        "text": "开放时间： 02月10日 12:00 - 03月10日 03:59"
      },
      {
        "type": "text",
        "text": "兑换说明： 活动期间，玩家可通过挑战活动关卡及【岁时考异】获取「未定稿」，消耗「未定稿」来兑换【天镜茶室】中物品"
      },
      {
        "type": "text",
        "text": "主要物品： 【矩】信物 、 【天镜阁会客堂】家具（部分） 、 寻访凭证 、时装 【0011制造系列 - 孤寒峭 - 絮雨】 、时装 【时代系列 - 光影 - 夜魔】、 模组养成材料、高级养成素材、龙门币、作战记录、家具零件等"
      },
      {
        "type": "text",
        "text": "◆本次活动期间【情报处理室】将无法浏览当期活动剧情，活动结束后该活动剧情将收录至【情报处理室】中"
      },
      {
        "type": "image",
        "src": "https://raw.githubusercontent.com/Jackie751/report/main/test/%E6%B4%BB%E5%8A%A8/2026___02___06_4942_%5B%E6%B4%BB%E5%8A%A8%E9%A2%84%E5%91%8A%5D%E8%BE%9E%E6%97%A7%E8%BF%8E%E6%96%B0%EF%BC%8CSideStory%E3%80%8C%E8%BE%9E%E5%B2%81%E8%A1%8C%E3%80%8D%E5%8D%B3%E5%B0%86%E5%BC%80%E5%90%AF/03_c6118fc204ca8726865ef5e144b610ac_07e250fe.jpg",
        "original_src": "https://web.hycdn.cn/upload/image/20260205/c6118fc204ca8726865ef5e144b610ac.jpg"
      },
      {
        "type": "text",
        "text": "二、【限定寻访·春节】系列，【劫尽古今】限定寻访开启"
      },
      {
        "type": "text",
        "text": "活动时间： 02月10日 12:00 - 02月24日 03:59"
      },
      {
        "type": "text",
        "text": "活动说明： 活动期间【限定寻访·春节】-【劫尽古今】寻访开启，该寻访中以下干员出现率上升"
      },
      {
        "type": "text",
        "text": "★★★★★★：望[限定]  \\  赤刃明霄陈 （占6★出率的70%）"
      },
      {
        "type": "text",
        "text": "★★★★★★：余[限定] \\ 黍[限定] \\ 重岳[限定] （在6★剩余出率【30%】中以5倍权值出率提升）"
      },
      {
        "type": "text",
        "text": "★★★★★：风絮 （占5★出率的50%）"
      },
      {
        "type": "image",
        "src": "https://raw.githubusercontent.com/Jackie751/report/main/test/%E6%B4%BB%E5%8A%A8/2026___02___06_4942_%5B%E6%B4%BB%E5%8A%A8%E9%A2%84%E5%91%8A%5D%E8%BE%9E%E6%97%A7%E8%BF%8E%E6%96%B0%EF%BC%8CSideStory%E3%80%8C%E8%BE%9E%E5%B2%81%E8%A1%8C%E3%80%8D%E5%8D%B3%E5%B0%86%E5%BC%80%E5%90%AF/04_f71cb99049794e35b2e9065a0fdfade2_204a777b.jpg",
        "original_src": "https://web.hycdn.cn/upload/image/20260205/f71cb99049794e35b2e9065a0fdfade2.jpg"
      },
      {
        "type": "text",
        "text": "在本期【限定寻访】中， 累计寻访300次，可以额外获得限定干员望（仅限一次） 。该次6星限定干员的获取是额外赠送，不产出【寻访数据契约】，同时也不会影响本期【限定寻访】获得下一个6星干员的概率，该累计次数会在本期【限定寻访】的结束时清零（后续【春节】、【庆典】、【夏季】系列限定寻访都将应用同类规则，即：寻访300次时，必定有获得1次额外领取当期限定干员的机会。这个规则的计数仅与该限定寻访绑定，不会跨寻访继承）"
      },
      {
        "type": "text",
        "text": "注意："
      },
      {
        "type": "text",
        "text": "◆【劫尽古今】为【限定寻访·春节】系列寻访"
      },
      {
        "type": "text",
        "text": "◆【限定寻访·春节】寻访为【限定寻访】"
      },
      {
        "type": "text",
        "text": "◆新增干员【赤刃明霄陈】、【风絮】除加入【限定寻访·春节】外，将在02月12日04:00后加入并常驻【标准寻访】卡池"
      },
      {
        "type": "text",
        "text": "◆新增干员【望】为【限定寻访·春节】限定干员，不会加入任何【标准寻访】"
      },
      {
        "type": "text",
        "text": "◆限定干员【望】在本次寻访结束后，将不会在2027年01月01日前加入任何【限定寻访】"
      },
      {
        "type": "text",
        "text": "◆ 干员【夕】将在【劫尽古今】限定寻访开启期间加入寻访数据契约交换所，且其交换所需寻访数据契约数量从该期交换所开始由300降低至200"
      },
      {
        "type": "text",
        "text": "本期寻访数据契约交换所可兑换干员："
      },
      {
        "type": "text",
        "text": "★★★★★★（300寻访数据契约）：望 \\ 赤刃明霄陈 \\ 余 \\ 黍 \\ 重岳 \\ 令"
      },
      {
        "type": "text",
        "text": "★★★★★★（200寻访数据契约）：夕 \\ 年"
      },
      {
        "type": "text",
        "text": "★★★★★（75寻访数据契约）：风絮"
      },
      {
        "type": "text",
        "text": "◆【限定寻访·春节】详细说明请参照相关卡池公告说明"
      },
      {
        "type": "image",
        "src": "https://raw.githubusercontent.com/Jackie751/report/main/test/%E6%B4%BB%E5%8A%A8/2026___02___06_4942_%5B%E6%B4%BB%E5%8A%A8%E9%A2%84%E5%91%8A%5D%E8%BE%9E%E6%97%A7%E8%BF%8E%E6%96%B0%EF%BC%8CSideStory%E3%80%8C%E8%BE%9E%E5%B2%81%E8%A1%8C%E3%80%8D%E5%8D%B3%E5%B0%86%E5%BC%80%E5%90%AF/05_2260c261243903c682e0188919892f30_feffee0b.jpg",
        "original_src": "https://web.hycdn.cn/upload/image/20260205/2260c261243903c682e0188919892f30.jpg"
      },
      {
        "type": "text",
        "text": "三、辞旧迎新，【劫尽古今】限时登录活动开启"
      },
      {
        "type": "text",
        "text": "活动说明： 玩家在活动期间进行登录即可在活动页面中领取登录奖励： [载月明归寻访凭证]*1"
      },
      {
        "type": "text",
        "text": "◆[载月明归寻访凭证]仅可用于【劫尽古今】寻访中进行一次十连寻访"
      },
      {
        "type": "text",
        "text": "◆[载月明归寻访凭证]过期时间为：2026年02月24日03:59"
      },
      {
        "type": "text",
        "text": "◆该登录奖励活动期间内每个账号仅可领取一次"
      },
      {
        "type": "image",
        "src": "https://raw.githubusercontent.com/Jackie751/report/main/test/%E6%B4%BB%E5%8A%A8/2026___02___06_4942_%5B%E6%B4%BB%E5%8A%A8%E9%A2%84%E5%91%8A%5D%E8%BE%9E%E6%97%A7%E8%BF%8E%E6%96%B0%EF%BC%8CSideStory%E3%80%8C%E8%BE%9E%E5%B2%81%E8%A1%8C%E3%80%8D%E5%8D%B3%E5%B0%86%E5%BC%80%E5%90%AF/06_4ced75c948496149cbcc29842cdbbc81_c5dfeeb9.jpg",
        "original_src": "https://web.hycdn.cn/upload/image/20260205/4ced75c948496149cbcc29842cdbbc81.jpg"
      },
      {
        "type": "text",
        "text": "四、辞旧迎新，【劫尽古今】限定寻访每日赠送"
      },
      {
        "type": "text",
        "text": "活动说明： 活动期间，玩家每日可在【劫尽古今】限定寻访中免费进行寻访一次"
      },
      {
        "type": "text",
        "text": "◆每日赠送寻访刷新时间为每日凌晨04:00"
      },
      {
        "type": "text",
        "text": "◆未进行使用的“每日赠送寻访”将在每日凌晨04:00进行刷新，无法进行累计"
      },
      {
        "type": "image",
        "src": "https://raw.githubusercontent.com/Jackie751/report/main/test/%E6%B4%BB%E5%8A%A8/2026___02___06_4942_%5B%E6%B4%BB%E5%8A%A8%E9%A2%84%E5%91%8A%5D%E8%BE%9E%E6%97%A7%E8%BF%8E%E6%96%B0%EF%BC%8CSideStory%E3%80%8C%E8%BE%9E%E5%B2%81%E8%A1%8C%E3%80%8D%E5%8D%B3%E5%B0%86%E5%BC%80%E5%90%AF/07_2d33b6ff6163eeafc49ee3f3c1998282_b18b8143.jpg",
        "original_src": "https://web.hycdn.cn/upload/image/20260205/2d33b6ff6163eeafc49ee3f3c1998282.jpg"
      },
      {
        "type": "text",
        "text": "五、辞旧迎新，新干员登场"
      },
      {
        "type": "text",
        "text": "★★★★★★：望[限定]"
      },
      {
        "type": "text",
        "text": "★★★★★★：赤刃明霄陈"
      },
      {
        "type": "text",
        "text": "★★★★★：风絮"
      },
      {
        "type": "text",
        "text": "★★★★★：矩"
      },
      {
        "type": "text",
        "text": "新增说明："
      },
      {
        "type": "text",
        "text": "◆新增干员【矩】仅在本次「辞岁行」活动中获取，暂不加入【劫尽古今】及任何【标准寻访】及【中坚寻访】"
      },
      {
        "type": "text",
        "text": "◆新增干员【赤刃明霄陈】、【风絮】除加入【劫尽古今】寻访外，将在02月12日04:00后加入并常驻其余【标准寻访】卡池"
      },
      {
        "type": "text",
        "text": "◆02月10日 12:00 - 03月03日 03:59以上新增干员活动关卡内信赖获取提升"
      },
      {
        "type": "image",
        "src": "https://raw.githubusercontent.com/Jackie751/report/main/test/%E6%B4%BB%E5%8A%A8/2026___02___06_4942_%5B%E6%B4%BB%E5%8A%A8%E9%A2%84%E5%91%8A%5D%E8%BE%9E%E6%97%A7%E8%BF%8E%E6%96%B0%EF%BC%8CSideStory%E3%80%8C%E8%BE%9E%E5%B2%81%E8%A1%8C%E3%80%8D%E5%8D%B3%E5%B0%86%E5%BC%80%E5%90%AF/08_01a15c86cab858fa9eb7a143ebf388c9_a2840f1f.jpg",
        "original_src": "https://web.hycdn.cn/upload/image/20260205/01a15c86cab858fa9eb7a143ebf388c9.jpg"
      },
      {
        "type": "text",
        "text": "六、辞旧迎新，鸣羽颂新签到活动开启"
      },
      {
        "type": "text",
        "text": "活动时间： 02月06日 21:00 - 03月10日 03:59"
      },
      {
        "type": "text",
        "text": "活动说明： 活动期间内，玩家登录即可领取 寻访凭证*1 、 活动头像【“新起点”】*1 奖励"
      },
      {
        "type": "image",
        "src": "https://raw.githubusercontent.com/Jackie751/report/main/test/%E6%B4%BB%E5%8A%A8/2026___02___06_4942_%5B%E6%B4%BB%E5%8A%A8%E9%A2%84%E5%91%8A%5D%E8%BE%9E%E6%97%A7%E8%BF%8E%E6%96%B0%EF%BC%8CSideStory%E3%80%8C%E8%BE%9E%E5%B2%81%E8%A1%8C%E3%80%8D%E5%8D%B3%E5%B0%86%E5%BC%80%E5%90%AF/09_086b5fca3b6e0814d5a1b4f9c3ce3c5b_51183dc8.jpg",
        "original_src": "https://web.hycdn.cn/upload/image/20260205/086b5fca3b6e0814d5a1b4f9c3ce3c5b.jpg"
      },
      {
        "type": "text",
        "text": "七、辞旧迎新，【龙门幸运墙】活动开启"
      },
      {
        "type": "text",
        "text": "活动说明： 活动期间玩家每日登录游戏后均可获得2次可选次数，在【龙门幸运墙】中消耗可选次数来进行游戏。在选取的幸运笺中，幸运笺所对应的合成玉数量最多的1张幸运笺为当日最终奖励，玩家需要用尽当日可选次数选取幸运笺，方可领取奖励"
      },
      {
        "type": "text",
        "text": "◆活动期间可进行抽取的天数最高为14个游戏日"
      },
      {
        "type": "text",
        "text": "◆幸运笺中可出现的合成玉数量为以下几档："
      },
      {
        "type": "text",
        "text": "（合成玉*200 、合成玉*300 、合成玉*400 、合成玉*500 、合成玉*600、合成玉*800）"
      },
      {
        "type": "text",
        "text": "◆当日幸运笺合成玉最终获得奖励不足400时（不含400），次日将增加一次可选次数。该次数不可累积叠加，玩家每日最多可获得的可选次数为3次（含每日登录赠送次数）"
      },
      {
        "type": "text",
        "text": "◆当日所有可选次数将在次日凌晨04:00 进行刷新，无法累计"
      },
      {
        "type": "image",
        "src": "https://raw.githubusercontent.com/Jackie751/report/main/test/%E6%B4%BB%E5%8A%A8/2026___02___06_4942_%5B%E6%B4%BB%E5%8A%A8%E9%A2%84%E5%91%8A%5D%E8%BE%9E%E6%97%A7%E8%BF%8E%E6%96%B0%EF%BC%8CSideStory%E3%80%8C%E8%BE%9E%E5%B2%81%E8%A1%8C%E3%80%8D%E5%8D%B3%E5%B0%86%E5%BC%80%E5%90%AF/10_488ee505fe7a31e09cbfcb0df4defdbb_58ba7c79.jpg",
        "original_src": "https://web.hycdn.cn/upload/image/20260205/488ee505fe7a31e09cbfcb0df4defdbb.jpg"
      },
      {
        "type": "text",
        "text": "八、辞旧迎新，新增表象载体系统"
      },
      {
        "type": "text",
        "text": "上线时间： 02月10日 12:00"
      },
      {
        "type": "text",
        "text": "更新说明： 02月10日 12:00版本更新后将新增表象载体系统，该系统由【时装回廊】、【个性化展厅】、【套组陈列室】及【形艺特辑】组成，将持续收录各类外观资源信息并提供主题套组收集奖励；其中，【形艺特辑】支持使用已持有的时装、个性外观资源和收藏贴对特辑封面进行自定义编辑，并可在名片中对外展示"
      },
      {
        "type": "text",
        "text": "◆以上详细功能介绍请关注后续官方自媒体相关内容"
      },
      {
        "type": "text",
        "text": "◆02月10日 12:00版本更新后，游戏关卡内将支持暂停时部署，同时玩家可在看板界面将动态立绘放至更大的比例，细节的观感也进行了一定提升"
      },
      {
        "type": "image",
        "src": "https://raw.githubusercontent.com/Jackie751/report/main/test/%E6%B4%BB%E5%8A%A8/2026___02___06_4942_%5B%E6%B4%BB%E5%8A%A8%E9%A2%84%E5%91%8A%5D%E8%BE%9E%E6%97%A7%E8%BF%8E%E6%96%B0%EF%BC%8CSideStory%E3%80%8C%E8%BE%9E%E5%B2%81%E8%A1%8C%E3%80%8D%E5%8D%B3%E5%B0%86%E5%BC%80%E5%90%AF/11_c3ff9119699c9a9572806dd0a6218ca3_ec1d3c4e.jpg",
        "original_src": "https://web.hycdn.cn/upload/image/20260205/c3ff9119699c9a9572806dd0a6218ca3.jpg"
      },
      {
        "type": "text",
        "text": "九、辞旧迎新，新增回忆画集系统"
      },
      {
        "type": "text",
        "text": "更新说明： 02月10日 12:00版本更新后将新增回忆画集系统，该系统可通过【曲谱】中的【本章回想】进入，玩家在该系统中可以回顾所有已解锁的画面CG，并选择喜爱的画面进行收藏"
      },
      {
        "type": "text",
        "text": "◆CG解锁条件：完成相应剧情的阅读（对于功能上线前已阅读的章节，将直接解锁对应CG内容）"
      },
      {
        "type": "text",
        "text": "◆详细功能介绍请关注后续官方自媒体相关内容"
      },
      {
        "type": "image",
        "src": "https://raw.githubusercontent.com/Jackie751/report/main/test/%E6%B4%BB%E5%8A%A8/2026___02___06_4942_%5B%E6%B4%BB%E5%8A%A8%E9%A2%84%E5%91%8A%5D%E8%BE%9E%E6%97%A7%E8%BF%8E%E6%96%B0%EF%BC%8CSideStory%E3%80%8C%E8%BE%9E%E5%B2%81%E8%A1%8C%E3%80%8D%E5%8D%B3%E5%B0%86%E5%BC%80%E5%90%AF/12_6f71b58b6d9895ece193fff6ad341e62_057c2aa4.jpg",
        "original_src": "https://web.hycdn.cn/upload/image/20260205/6f71b58b6d9895ece193fff6ad341e62.jpg"
      },
      {
        "type": "text",
        "text": "十、《明日方舟》PC端技术性开放测试开启"
      },
      {
        "type": "text",
        "text": "测试说明： 《明日方舟》PC端技术性开放测试将于02月10日开启，PC端中进行了键盘、鼠标的操作适配，玩家可在端内设置中自由调节具体键位；此外，PC端还支持最高120帧的高帧率模式，玩家可以在端内设置中调整帧率选项"
      },
      {
        "type": "text",
        "text": "◆本次测试为不限量测试，且PC端和移动端实现了同服数据互通，官服和B服的玩家都可以在对应渠道的PC端上进行体验"
      },
      {
        "type": "image",
        "src": "https://raw.githubusercontent.com/Jackie751/report/main/test/%E6%B4%BB%E5%8A%A8/2026___02___06_4942_%5B%E6%B4%BB%E5%8A%A8%E9%A2%84%E5%91%8A%5D%E8%BE%9E%E6%97%A7%E8%BF%8E%E6%96%B0%EF%BC%8CSideStory%E3%80%8C%E8%BE%9E%E5%B2%81%E8%A1%8C%E3%80%8D%E5%8D%B3%E5%B0%86%E5%BC%80%E5%90%AF/13_ddab410e82058a8f245b2a2662ca304c_581a4a24.jpg",
        "original_src": "https://web.hycdn.cn/upload/image/20260205/ddab410e82058a8f245b2a2662ca304c.jpg"
      },
      {
        "type": "text",
        "text": "十一、辞旧迎新，新装限时上架"
      },
      {
        "type": "text",
        "text": "贩售时间： 02月10日 12:00 - 03月10日 03:59"
      },
      {
        "type": "text",
        "text": "活动说明： 活动期间以下干员新增时装将在时装商店上架并限时贩售"
      },
      {
        "type": "text",
        "text": "◆【0011制造】系列 - 方遒卷 - 令"
      },
      {
        "type": "text",
        "text": "◆【0011制造】系列 - 青玉砚 - 夕"
      },
      {
        "type": "text",
        "text": "◆【0011制造】系列 - 愿清晓 - 余"
      },
      {
        "type": "text",
        "text": "◆【0011制造】系列 - 共凭栏 - 寻澜"
      },
      {
        "type": "text",
        "text": "◆【0011制造】系列 - 花绸曲 - 菲莱"
      },
      {
        "type": "image",
        "src": "https://raw.githubusercontent.com/Jackie751/report/main/test/%E6%B4%BB%E5%8A%A8/2026___02___06_4942_%5B%E6%B4%BB%E5%8A%A8%E9%A2%84%E5%91%8A%5D%E8%BE%9E%E6%97%A7%E8%BF%8E%E6%96%B0%EF%BC%8CSideStory%E3%80%8C%E8%BE%9E%E5%B2%81%E8%A1%8C%E3%80%8D%E5%8D%B3%E5%B0%86%E5%BC%80%E5%90%AF/14_bb0194b579bbf582345a3669442d79ed_1f45041f.jpg",
        "original_src": "https://web.hycdn.cn/upload/image/20260205/bb0194b579bbf582345a3669442d79ed.jpg"
      },
      {
        "type": "text",
        "text": "十二、辞旧迎新，迎春组合包限时上架"
      },
      {
        "type": "text",
        "text": "售卖时间： 02月10日 12:00 - 03月10日 03:59"
      },
      {
        "type": "text",
        "text": "活动说明： 活动期间，采购中心将限时售卖以下组合包"
      },
      {
        "type": "text",
        "text": "[天镜珍藏组合包]"
      },
      {
        "type": "text",
        "text": "组合包内容： 至纯源石*24、十连寻访凭证*2、龙门币*200000、高级作战记录*20、中级作战记录*30、芯片助剂*2、特级材料提货券*4、高级材料提货券*6"
      },
      {
        "type": "text",
        "text": "[新春养成组合包]"
      },
      {
        "type": "text",
        "text": "组合包内容： 合成玉*5000、龙门币*100000、芯片助剂*2、中级作战记录*30"
      },
      {
        "type": "text",
        "text": "[望的手提箱]"
      },
      {
        "type": "text",
        "text": "组合包内容： 至纯源石*16、龙门币*700000"
      },
      {
        "type": "image",
        "src": "https://raw.githubusercontent.com/Jackie751/report/main/test/%E6%B4%BB%E5%8A%A8/2026___02___06_4942_%5B%E6%B4%BB%E5%8A%A8%E9%A2%84%E5%91%8A%5D%E8%BE%9E%E6%97%A7%E8%BF%8E%E6%96%B0%EF%BC%8CSideStory%E3%80%8C%E8%BE%9E%E5%B2%81%E8%A1%8C%E3%80%8D%E5%8D%B3%E5%B0%86%E5%BC%80%E5%90%AF/15_59754a47fa5f1c93c19ad98a9ff4011f_9d0bf19e.jpg",
        "original_src": "https://web.hycdn.cn/upload/image/20260205/59754a47fa5f1c93c19ad98a9ff4011f.jpg"
      },
      {
        "type": "text",
        "text": "[罗德岛迎春组合包]"
      },
      {
        "type": "text",
        "text": "组合包内容： 至纯源石*90、时装自选凭证*1、十连寻访凭证*1、十连中坚寻访凭证*1、龙门币*260000、高级作战记录*30、芯片助剂*4、模组数据块*6、数据增补仪*30、数据增补条*90"
      },
      {
        "type": "text",
        "text": "[新春贺礼补给包]"
      },
      {
        "type": "text",
        "text": "组合包内容： 至纯源石*30、时装自选凭证*1、自助芯片组印刻仪*1、高级材料提货券*8、中级作战记录*50、龙门币*100000"
      },
      {
        "type": "text",
        "text": "[高级特训意向礼包]"
      },
      {
        "type": "text",
        "text": "组合包内容： 至纯源石*19、 高级资深干员特训装置*1"
      },
      {
        "type": "text",
        "text": "高级资深干员特训装置 ：使用该特训装置后可选择一名已晋升至精英阶段2的6星干员直接升至精英阶段2，等级90。干员升级后不会返还已投入的养成资源"
      },
      {
        "type": "text",
        "text": "[特训意向礼包]"
      },
      {
        "type": "text",
        "text": "组合包内容： 至纯源石*11、 资深干员特训装置*1"
      },
      {
        "type": "text",
        "text": "资深干员特训装置 ：使用该特训装置后可选择一名已晋升至精英阶段2的5星干员直接升至精英阶段2，等级80。干员升级后不会返还已投入的养成资源"
      },
      {
        "type": "image",
        "src": "https://raw.githubusercontent.com/Jackie751/report/main/test/%E6%B4%BB%E5%8A%A8/2026___02___06_4942_%5B%E6%B4%BB%E5%8A%A8%E9%A2%84%E5%91%8A%5D%E8%BE%9E%E6%97%A7%E8%BF%8E%E6%96%B0%EF%BC%8CSideStory%E3%80%8C%E8%BE%9E%E5%B2%81%E8%A1%8C%E3%80%8D%E5%8D%B3%E5%B0%86%E5%BC%80%E5%90%AF/16_824dcfd5983fffc29df8f7064302b2f2_168b9106.jpg",
        "original_src": "https://web.hycdn.cn/upload/image/20260205/824dcfd5983fffc29df8f7064302b2f2.jpg"
      },
      {
        "type": "text",
        "text": "[新春祝愿补给包]"
      },
      {
        "type": "text",
        "text": "组合包内容： 寻访凭证*1、中坚寻访凭证*1、模组数据块*1、龙门币*10000"
      },
      {
        "type": "text",
        "text": "[技巧集综合礼包] （限购两次）"
      },
      {
        "type": "text",
        "text": "组合包内容： 至纯源石*12、 高级资深干员技巧集*1 、 资深干员技巧集*1 、 专业干员技巧集*1"
      },
      {
        "type": "text",
        "text": "高级资深干员技巧集： 可以选择一个满足专精条件的6星干员的技能，提升至专精3级"
      },
      {
        "type": "text",
        "text": "[中坚寻访组合包]（限购两次）"
      },
      {
        "type": "text",
        "text": "组合包内容： 十连中坚寻访凭证*1"
      },
      {
        "type": "image",
        "src": "https://raw.githubusercontent.com/Jackie751/report/main/test/%E6%B4%BB%E5%8A%A8/2026___02___06_4942_%5B%E6%B4%BB%E5%8A%A8%E9%A2%84%E5%91%8A%5D%E8%BE%9E%E6%97%A7%E8%BF%8E%E6%96%B0%EF%BC%8CSideStory%E3%80%8C%E8%BE%9E%E5%B2%81%E8%A1%8C%E3%80%8D%E5%8D%B3%E5%B0%86%E5%BC%80%E5%90%AF/17_75b1dfb4b641d54fb7ab5999d785220a_60e04255.jpg",
        "original_src": "https://web.hycdn.cn/upload/image/20260205/75b1dfb4b641d54fb7ab5999d785220a.jpg"
      },
      {
        "type": "text",
        "text": "[近卫芯片礼包]"
      },
      {
        "type": "text",
        "text": "组合包内容： 近卫双芯片*4、近卫芯片*5、技巧概要·卷3*45、技巧概要·卷2*25、技巧概要·卷1*10"
      },
      {
        "type": "text",
        "text": "[特种芯片礼包]"
      },
      {
        "type": "text",
        "text": "组合包内容： 特种双芯片*4、特种芯片*5、技巧概要·卷3*45、技巧概要·卷2*25、技巧概要·卷1*10"
      },
      {
        "type": "image",
        "src": "https://raw.githubusercontent.com/Jackie751/report/main/test/%E6%B4%BB%E5%8A%A8/2026___02___06_4942_%5B%E6%B4%BB%E5%8A%A8%E9%A2%84%E5%91%8A%5D%E8%BE%9E%E6%97%A7%E8%BF%8E%E6%96%B0%EF%BC%8CSideStory%E3%80%8C%E8%BE%9E%E5%B2%81%E8%A1%8C%E3%80%8D%E5%8D%B3%E5%B0%86%E5%BC%80%E5%90%AF/18_3ed9f3049e0b3b35c658dfeb4b35abf0_313967ac.jpg",
        "original_src": "https://web.hycdn.cn/upload/image/20260205/3ed9f3049e0b3b35c658dfeb4b35abf0.jpg"
      },
      {
        "type": "text",
        "text": "十三、辞旧迎新，新增主题家具限时获取"
      },
      {
        "type": "text",
        "text": "活动说明： 活动期间新增活动限定家具【余味居后厨】系列与【天镜阁会客堂】系列"
      },
      {
        "type": "text",
        "text": "【余味居后厨】系列"
      },
      {
        "type": "text",
        "text": "获取方式："
      },
      {
        "type": "text",
        "text": "◆家具商店限时售卖：02月10日 12:00 - 03月10日 03:59"
      },
      {
        "type": "image",
        "src": "https://raw.githubusercontent.com/Jackie751/report/main/test/%E6%B4%BB%E5%8A%A8/2026___02___06_4942_%5B%E6%B4%BB%E5%8A%A8%E9%A2%84%E5%91%8A%5D%E8%BE%9E%E6%97%A7%E8%BF%8E%E6%96%B0%EF%BC%8CSideStory%E3%80%8C%E8%BE%9E%E5%B2%81%E8%A1%8C%E3%80%8D%E5%8D%B3%E5%B0%86%E5%BC%80%E5%90%AF/19_b112dacde2ba029f2ca3fad2bfbcb3eb_22503c72.jpg",
        "original_src": "https://web.hycdn.cn/upload/image/20260205/b112dacde2ba029f2ca3fad2bfbcb3eb.jpg"
      },
      {
        "type": "text",
        "text": "【天镜阁会客堂】系列"
      },
      {
        "type": "text",
        "text": "◆SideStory「辞岁行」活动奖励及兑换（部分）"
      },
      {
        "type": "text",
        "text": "◆家具商店限时售卖（部分）：02月10日 12:00 - 03月10日 03:59"
      },
      {
        "type": "image",
        "src": "https://raw.githubusercontent.com/Jackie751/report/main/test/%E6%B4%BB%E5%8A%A8/2026___02___06_4942_%5B%E6%B4%BB%E5%8A%A8%E9%A2%84%E5%91%8A%5D%E8%BE%9E%E6%97%A7%E8%BF%8E%E6%96%B0%EF%BC%8CSideStory%E3%80%8C%E8%BE%9E%E5%B2%81%E8%A1%8C%E3%80%8D%E5%8D%B3%E5%B0%86%E5%BC%80%E5%90%AF/20_a89d12af157abcbc9bf208682bf297e9_7bf7c2ee.jpg",
        "original_src": "https://web.hycdn.cn/upload/image/20260205/a89d12af157abcbc9bf208682bf297e9.jpg"
      },
      {
        "type": "text",
        "text": "十四、辞旧迎新，新增特限模组"
      },
      {
        "type": "text",
        "text": "更新时间： 02月10日 12:00"
      },
      {
        "type": "text",
        "text": "活动内容： 新增以下干员的特限模组："
      },
      {
        "type": "text",
        "text": "★★★★★★：艾丽妮 （该特限模组在 集成战略 中生效对应机制）"
      },
      {
        "type": "text",
        "text": "★★★★★★：异客 （该特限模组在 生息演算 中生效对应机制）"
      },
      {
        "type": "image",
        "src": "https://raw.githubusercontent.com/Jackie751/report/main/test/%E6%B4%BB%E5%8A%A8/2026___02___06_4942_%5B%E6%B4%BB%E5%8A%A8%E9%A2%84%E5%91%8A%5D%E8%BE%9E%E6%97%A7%E8%BF%8E%E6%96%B0%EF%BC%8CSideStory%E3%80%8C%E8%BE%9E%E5%B2%81%E8%A1%8C%E3%80%8D%E5%8D%B3%E5%B0%86%E5%BC%80%E5%90%AF/21_b08cacd2b1655797191f82430e7e505d_e8cf23db.jpg",
        "original_src": "https://web.hycdn.cn/upload/image/20260205/b08cacd2b1655797191f82430e7e505d.jpg"
      },
      {
        "type": "text",
        "text": "十五、辞旧迎新，【公开招募】干员更新"
      },
      {
        "type": "text",
        "text": "更新说明：更新后，以下干员将加入并常驻【公开招募】"
      },
      {
        "type": "text",
        "text": "★★★★★★ 卡涅利安"
      },
      {
        "type": "text",
        "text": "★★★★★ 绮良"
      },
      {
        "type": "text",
        "text": "★★★★ 深靛"
      },
      {
        "type": "text",
        "text": "本次【公开招募】干员更新时，将对未开始进行招募的标签进行强制刷新，强制刷新注意事项及相关补偿请参照官方相关更新公告"
      },
      {
        "type": "image",
        "src": "https://raw.githubusercontent.com/Jackie751/report/main/test/%E6%B4%BB%E5%8A%A8/2026___02___06_4942_%5B%E6%B4%BB%E5%8A%A8%E9%A2%84%E5%91%8A%5D%E8%BE%9E%E6%97%A7%E8%BF%8E%E6%96%B0%EF%BC%8CSideStory%E3%80%8C%E8%BE%9E%E5%B2%81%E8%A1%8C%E3%80%8D%E5%8D%B3%E5%B0%86%E5%BC%80%E5%90%AF/22_f742220cb747f751db1c28d368e51655_50c59dea.jpg",
        "original_src": "https://web.hycdn.cn/upload/image/20260205/f742220cb747f751db1c28d368e51655.jpg"
      },
      {
        "type": "text",
        "text": "十六、辞旧迎新，采购中心可兑换内容追加"
      },
      {
        "type": "text",
        "text": "活动内容： 采购中心凭证交易所【高级凭证区】&【通用凭证区】将新增上架以下内容可供兑换："
      },
      {
        "type": "text",
        "text": "时装【斗争血脉】系列 - 无畏 - 米格鲁"
      },
      {
        "type": "image",
        "src": "https://raw.githubusercontent.com/Jackie751/report/main/test/%E6%B4%BB%E5%8A%A8/2026___02___06_4942_%5B%E6%B4%BB%E5%8A%A8%E9%A2%84%E5%91%8A%5D%E8%BE%9E%E6%97%A7%E8%BF%8E%E6%96%B0%EF%BC%8CSideStory%E3%80%8C%E8%BE%9E%E5%B2%81%E8%A1%8C%E3%80%8D%E5%8D%B3%E5%B0%86%E5%BC%80%E5%90%AF/23_0addea6272620ee7cd48c3aad6d5888b_52177454.jpg",
        "original_src": "https://web.hycdn.cn/upload/image/20260205/0addea6272620ee7cd48c3aad6d5888b.jpg"
      },
      {
        "type": "text",
        "text": "十七、辞旧迎新，2026罗德岛新春签到开启"
      },
      {
        "type": "text",
        "text": "活动时间： 02月16日 04:00 - 03月02日 03:59"
      },
      {
        "type": "text",
        "text": "活动说明： 活动期间内，玩家在除夕、初一、初五及初八登录可随机获得特定干员的祝福， 收到祝福后可获得一定数量的合成玉并纳入祝辞集 ，且干员祝福可被分享或保存为壁纸。玩家累计签到10日还可获得活动家具、模组养成材料、应急理智浓缩液等活动奖励"
      },
      {
        "type": "text",
        "text": "累计签到第一日：应急理智浓缩液*1、龙门币*30000"
      },
      {
        "type": "text",
        "text": "累计签到第二日：中级作战记录*20、招聘许可*5"
      },
      {
        "type": "text",
        "text": "累计签到第三日：芯片助剂*1、技巧概要·卷2*20"
      },
      {
        "type": "text",
        "text": "累计签到第四日：高级作战记录*10、糖组*3"
      },
      {
        "type": "text",
        "text": "累计签到第五日：龙门币*30000、加急许可*5"
      },
      {
        "type": "text",
        "text": "累计签到第六日：技巧概要·卷3*8、晶体元件*3"
      },
      {
        "type": "text",
        "text": "累计签到第七日：数据增补仪*3、赤金*20"
      },
      {
        "type": "text",
        "text": "累计签到第八日： 家具【“贺佳节”灯箱】*1 、家具零件*300"
      },
      {
        "type": "text",
        "text": "累计签到第九日：数据增补条*10、固源岩组*3"
      },
      {
        "type": "text",
        "text": "累计签到第十日：模组数据块*1、技巧概要·卷1*30"
      },
      {
        "type": "text",
        "text": "◆除对应节点登录外，玩家还可以通过累计登录获得干员祝辞（每个节点的干员祝辞解锁后只能获得一次，不可重复获得）"
      },
      {
        "type": "text",
        "text": "◆本次签到活动中领取的“应急理智浓缩液”到期时间请以游戏内显示为准"
      },
      {
        "type": "image",
        "src": "https://raw.githubusercontent.com/Jackie751/report/main/test/%E6%B4%BB%E5%8A%A8/2026___02___06_4942_%5B%E6%B4%BB%E5%8A%A8%E9%A2%84%E5%91%8A%5D%E8%BE%9E%E6%97%A7%E8%BF%8E%E6%96%B0%EF%BC%8CSideStory%E3%80%8C%E8%BE%9E%E5%B2%81%E8%A1%8C%E3%80%8D%E5%8D%B3%E5%B0%86%E5%BC%80%E5%90%AF/24_8a156aefaea93263276f5911d8f0fa5d_cfb73059.jpg",
        "original_src": "https://web.hycdn.cn/upload/image/20260205/8a156aefaea93263276f5911d8f0fa5d.jpg"
      },
      {
        "type": "text",
        "text": "十八、辞旧迎新，除夕夜特别登录奖励开启"
      },
      {
        "type": "text",
        "text": "活动时间： 02月16日 20:00 - 24:00"
      },
      {
        "type": "text",
        "text": "活动说明： 玩家可在活动期间不同时段领取来自不同干员的邮件赠礼"
      },
      {
        "type": "text",
        "text": "领取范围： 2026年02月17日00:00前所有注册并创建角色的玩家"
      },
      {
        "type": "text",
        "text": "注意事项："
      },
      {
        "type": "text",
        "text": "◆赠礼内容及发放时间请以游戏内实际发放为准"
      },
      {
        "type": "text",
        "text": "◆该活动邮件有效期为7天，请在收到该邮件后尽快领取"
      },
      {
        "type": "image",
        "src": "https://raw.githubusercontent.com/Jackie751/report/main/test/%E6%B4%BB%E5%8A%A8/2026___02___06_4942_%5B%E6%B4%BB%E5%8A%A8%E9%A2%84%E5%91%8A%5D%E8%BE%9E%E6%97%A7%E8%BF%8E%E6%96%B0%EF%BC%8CSideStory%E3%80%8C%E8%BE%9E%E5%B2%81%E8%A1%8C%E3%80%8D%E5%8D%B3%E5%B0%86%E5%BC%80%E5%90%AF/25_5056ba41e65e3c326986318148ab08f0_6062c0ec.jpg",
        "original_src": "https://web.hycdn.cn/upload/image/20260206/5056ba41e65e3c326986318148ab08f0.jpg"
      },
      {
        "type": "text",
        "text": "十九、辞旧迎新，中坚甄选开启"
      },
      {
        "type": "text",
        "text": "活动时间： 02月19日 04:00 - 03月05日 03:59"
      },
      {
        "type": "text",
        "text": "活动说明： 活动期间，玩家可以 在当期甄选的干员范围内自主选择并锁定 2位六星干员和3位五星干员作为当期【中坚甄选】寻访出现概率提升的干员。相应地，原【高级凭证区】和【通用凭证区】内可兑换的【中坚寻访】中出率上升的干员，在【中坚甄选】期间将转变为：在当期【中坚甄选】寻访获得概率提升的干员范围内自行选定1位六星干员和1位五星干员进入【高级凭证区】和【通用凭证区】内可供兑换"
      },
      {
        "type": "text",
        "text": "当期甄选的干员范围："
      },
      {
        "type": "text",
        "text": "★★★★★★（出率2%）：水月/远牙/泥岩/山/铃兰/早露/风笛/推进之王/陈/安洁莉娜/傀影/麦哲伦"
      },
      {
        "type": "text",
        "text": "★★★★★（出率8%）：灰毫/拉普兰德/絮雨/安哲拉/幽灵鲨/卡夫卡/白金/陨星/槐琥/真理/四月/断崖/蜜蜡/芙兰卡/普罗旺斯/石棉/布洛卡/吽/乌有/熔泉/诗怀雅/慑砂/月禾/燧石"
      },
      {
        "type": "text",
        "text": "注意： 【中坚甄选】会继承切换前的常驻【中坚寻访】六星干员获得概率"
      },
      {
        "type": "image",
        "src": "https://raw.githubusercontent.com/Jackie751/report/main/test/%E6%B4%BB%E5%8A%A8/2026___02___06_4942_%5B%E6%B4%BB%E5%8A%A8%E9%A2%84%E5%91%8A%5D%E8%BE%9E%E6%97%A7%E8%BF%8E%E6%96%B0%EF%BC%8CSideStory%E3%80%8C%E8%BE%9E%E5%B2%81%E8%A1%8C%E3%80%8D%E5%8D%B3%E5%B0%86%E5%BC%80%E5%90%AF/26_c016b705c9d7b880f5229d1e90ab2eec_9d0130a4.jpg",
        "original_src": "https://web.hycdn.cn/upload/image/20260205/c016b705c9d7b880f5229d1e90ab2eec.jpg"
      },
      {
        "type": "text",
        "text": "二十、【待予花冠】系列，新装限时上架"
      },
      {
        "type": "text",
        "text": "活动时间： 02月14日 04:00 - 02月28日 03:59"
      },
      {
        "type": "text",
        "text": "活动说明： 活动期间以下干员新增时装将在时装商店上架并限时贩售："
      },
      {
        "type": "text",
        "text": "◆【待予花冠】系列 - 半甜草莓 - 微风"
      },
      {
        "type": "text",
        "text": "◆【待予花冠】系列 - 红丝带之约 - 豆苗"
      },
      {
        "type": "image",
        "src": "https://raw.githubusercontent.com/Jackie751/report/main/test/%E6%B4%BB%E5%8A%A8/2026___02___06_4942_%5B%E6%B4%BB%E5%8A%A8%E9%A2%84%E5%91%8A%5D%E8%BE%9E%E6%97%A7%E8%BF%8E%E6%96%B0%EF%BC%8CSideStory%E3%80%8C%E8%BE%9E%E5%B2%81%E8%A1%8C%E3%80%8D%E5%8D%B3%E5%B0%86%E5%BC%80%E5%90%AF/27_e2e04a4144699451991a2236597bf106_ddd8545c.jpg",
        "original_src": "https://web.hycdn.cn/upload/image/20260205/e2e04a4144699451991a2236597bf106.jpg"
      },
      {
        "type": "text",
        "text": "二十一、【待予花冠】系列，限时复刻上架"
      },
      {
        "type": "text",
        "text": "活动说明： 活动期间以下干员时装将在时装商店上架并限时贩售："
      },
      {
        "type": "text",
        "text": "◆【待予花冠】系列 - 湖畔的少女 - 夜魔"
      },
      {
        "type": "text",
        "text": "◆【待予花冠】系列 - 浪漫满厢 - 濯尘芙蓉"
      },
      {
        "type": "image",
        "src": "https://raw.githubusercontent.com/Jackie751/report/main/test/%E6%B4%BB%E5%8A%A8/2026___02___06_4942_%5B%E6%B4%BB%E5%8A%A8%E9%A2%84%E5%91%8A%5D%E8%BE%9E%E6%97%A7%E8%BF%8E%E6%96%B0%EF%BC%8CSideStory%E3%80%8C%E8%BE%9E%E5%B2%81%E8%A1%8C%E3%80%8D%E5%8D%B3%E5%B0%86%E5%BC%80%E5%90%AF/28_1a8c81dcd6fc1ef146dac56f3fa1bb92_d2d31a69.jpg",
        "original_src": "https://web.hycdn.cn/upload/image/20260205/1a8c81dcd6fc1ef146dac56f3fa1bb92.jpg"
      },
      {
        "type": "text",
        "text": "◆【 待予花冠】系列 - 装点 - 和弦"
      },
      {
        "type": "text",
        "text": "◆【 待予花冠】系列 - 危险邀约 - 芳汀"
      },
      {
        "type": "text",
        "text": "更多活动内容请持续关注《明日方舟》游戏内公告及官方公告。"
      },
      {
        "type": "text",
        "text": "【明日方舟】运营组"
      },
      {
        "type": "text",
        "text": "2026年02月06日"
      }
    ]
  }
]